Workbook

Sheet 财务流水
A1: 财务流水明细台账
A3: 填写提示：金额统一录入正数，业务类型决定收入或支出；黄色列为人工录入，绿色列为自动计算。
A4: 日期 | B4: 月份 | C4: 业务类型 | D4: 部门 | E4: 项目/站点 | F4: 费用类别 | G4: 摘要 | H4: 对方单位 | I4: 发票状态 | J4: 支付状态 | K4: 付款方式 | L4: 金额(含税) | M4: 税率 | N4: 税额 | O4: 未税金额 | P4: 经办人 | Q4: 异常检查
A5: 46028 | B5: =TEXT(A5,"yyyy-mm") | C5: 收入 | D5: 运营部 | E5: 金坛体育馆站 | F5: 充电服务收入 | G5: 1月充电服务收入 | H5: 常州某运营公司 | I5: 已开票 | J5: 已收款 | K5: 银行转账 | L5: 286000 | M5: 0.06 | N5: =IFERROR(L5*M5/(1+M5),0) | O5: =L5-N5 | P5: 张敏 | Q5: =IF(A5="","",IF(OR(L5<=0,C5="",D5="",F5=""),"需检查",IF(AND(C5="支出",I5="未收票"),"缺发票","正常")))
A6: 46032 | B6: =TEXT(A6,"yyyy-mm") | C6: 支出 | D6: 研发部 | E6: AI平台一期 | F6: 软件服务费 | G6: 模型API及云资源 | H6: 某科技公司 | I6: 已收票 | J6: 已付款 | K6: 银行转账 | L6: 38000 | M6: 0.06 | N6: =IFERROR(L6*M6/(1+M6),0) | O6: =L6-N6 | P6: 李强 | Q6: =IF(A6="","",IF(OR(L6<=0,C6="",D6="",F6=""),"需检查",IF(AND(C6="支出",I6="未收票"),"缺发票","正常")))
A7: 46040 | B7: =TEXT(A7,"yyyy-mm") | C7: 支出 | D7: 运营部 | E7: 金坛体育馆站 | F7: 电费 | G7: 1月场站购电费 | H7: 国网常州供电公司 | I7: 已收票 | J7: 已付款 | K7: 银行转账 | L7: 92000 | M7: 0.13 | N7: =IFERROR(L7*M7/(1+M7),0) | O7: =L7-N7 | P7: 王芳 | Q7: =IF(A7="","",IF(OR(L7<=0,C7="",D7="",F7=""),"需检查",IF(AND(C7="支出",I7="未收票"),"缺发票","正常")))
A8: 46061 | B8: =TEXT(A8,"yyyy-mm") | C8: 收入 | D8: 运营部 | E8: 弘阳广场站 | F8: 充电服务收入 | G8: 2月充电服务收入 | H8: 常州某运营公司 | I8: 已开票 | J8: 已收款 | K8: 银行转账 | L8: 301000 | M8: 0.06 | N8: =IFERROR(L8*M8/(1+M8),0) | O8: =L8-N8 | P8: 张敏 | Q8: =IF(A8="","",IF(OR(L8<=0,C8="",D8="",F8=""),"需检查",IF(AND(C8="支出",I8="未收票"),"缺发票","正常")))
A9: 46068 | B9: =TEXT(A9,"yyyy-mm") | C9: 支出 | D9: 市场部 | E9: 品牌推广 | F9: 市场推广费 | G9: 行业会议展位费 | H9: 某会展公司 | I9: 已收票 | J9: 已付款 | K9: 公司卡 | L9: 26000 | M9: 0.06 | N9: =IFERROR(L9*M9/(1+M9),0) | O9: =L9-N9 | P9: 赵晨 | Q9: =IF(A9="","",IF(OR(L9<=0,C9="",D9="",F9=""),"需检查",IF(AND(C9="支出",I9="未收票"),"缺发票","正常")))
A10: 46086 | B10: =TEXT(A10,"yyyy-mm") | C10: 收入 | D10: 项目部 | E10: 储能改造项目 | F10: 项目服务收入 | G10: 储能EMS实施款 | H10: 某能源公司 | I10: 已开票 | J10: 部分收款 | K10: 银行转账 | L10: 420000 | M10: 0.06 | N10: =IFERROR(L10*M10/(1+M10),0) | O10: =L10-N10 | P10: 陈杰 | Q10: =IF(A10="","",IF(OR(L10<=0,C10="",D10="",F10=""),"需检查",IF(AND(C10="支出",I10="未收票"),"缺发票","正常")))
A11: 46092 | B11: =TEXT(A11,"yyyy-mm") | C11: 支出 | D11: 项目部 | E11: 储能改造项目 | F11: 设备采购 | G11: 储能计量设备采购 | H11: 某设备公司 | I11: 已收票 | J11: 已付款 | K11: 银行转账 | L11: 185000 | M11: 0.13 | N11: =IFERROR(L11*M11/(1+M11),0) | O11: =L11-N11 | P11: 陈杰 | Q11: =IF(A11="","",IF(OR(L11<=0,C11="",D11="",F11=""),"需检查",IF(AND(C11="支出",I11="未收票"),"缺发票","正常")))
A12: 46121 | B12: =TEXT(A12,"yyyy-mm") | C12: 支出 | D12: 行政部 | E12: 总部 | F12: 办公费 | G12: 办公耗材采购 | H12: 某商贸公司 | I12: 已收票 | J12: 已付款 | K12: 公司卡 | L12: 12800 | M12: 0.13 | N12: =IFERROR(L12*M12/(1+M12),0) | O12: =L12-N12 | P12: 刘悦 | Q12: =IF(A12="","",IF(OR(L12<=0,C12="",D12="",F12=""),"需检查",IF(AND(C12="支出",I12="未收票"),"缺发票","正常")))
A13: 46137 | B13: =TEXT(A13,"yyyy-mm") | C13: 收入 | D13: 运营部 | E13: 凤凰谷站 | F13: 充电服务收入 | G13: 4月充电服务收入 | H13: 常州某运营公司 | I13: 已开票 | J13: 已收款 | K13: 银行转账 | L13: 318000 | M13: 0.06 | N13: =IFERROR(L13*M13/(1+M13),0) | O13: =L13-N13 | P13: 张敏 | Q13: =IF(A13="","",IF(OR(L13<=0,C13="",D13="",F13=""),"需检查",IF(AND(C13="支出",I13="未收票"),"缺发票","正常")))
A14: 46148 | B14: =TEXT(A14,"yyyy-mm") | C14: 支出 | D14: 研发部 | E14: AI平台一期 | F14: 差旅费 | G14: 项目调研差旅 | H14: 个人报销 | I14: 无需发票 | J14: 已付款 | K14: 个人垫付 | L14: 8600 | M14: 0 | N14: =IFERROR(L14*M14/(1+M14),0) | O14: =L14-N14 | P14: 李强 | Q14: =IF(A14="","",IF(OR(L14<=0,C14="",D14="",F14=""),"需检查",IF(AND(C14="支出",I14="未收票"),"缺发票","正常")))
A15: 46162 | B15: =TEXT(A15,"yyyy-mm") | C15: 支出 | D15: 运营部 | E15: 凤凰谷站 | F15: 运维费 | G15: 充电桩年度巡检 | H15: 某运维公司 | I15: 未收票 | J15: 未付款 | K15: 银行转账 | L15: 46000 | M15: 0.06 | N15: =IFERROR(L15*M15/(1+M15),0) | O15: =L15-N15 | P15: 王芳 | Q15: =IF(A15="","",IF(OR(L15<=0,C15="",D15="",F15=""),"需检查",IF(AND(C15="支出",I15="未收票"),"缺发票","正常")))
A16: 46176 | B16: =TEXT(A16,"yyyy-mm") | C16: 收入 | D16: 项目部 | E16: 数据平台项目 | F16: 项目服务收入 | G16: 数据平台二期里程碑款 | H16: 某电力公司 | I16: 已开票 | J16: 已收款 | K16: 银行转账 | L16: 560000 | M16: 0.06 | N16: =IFERROR(L16*M16/(1+M16),0) | O16: =L16-N16 | P16: 陈杰 | Q16: =IF(A16="","",IF(OR(L16<=0,C16="",D16="",F16=""),"需检查",IF(AND(C16="支出",I16="未收票"),"缺发票","正常")))
... A22: 46218 | B22: =TEXT(A22,"yyyy-mm") | C22: 收入 | D22: 项目部 | E22: 数据平台项目 | F22: 项目服务收入 | G22: 验收尾款 | H22: 某电力公司 | I22: 未开票 | J22: 未收款 | K22: 银行转账 | L22: 220000 | M22: 0.06 | N22: =IFERROR(L22*M22/(1+M22),0) | O22: =L22-N22 | P22: 陈杰 | Q22: =IF(A22="","",IF(OR(L22<=0,C22="",D22="",F22=""),"需检查",IF(AND(C22="支出",I22="未收票"),"缺发票","正常")))
B23: =TEXT(A23,"yyyy-mm") | N23: =IFERROR(L23*M23/(1+M23),0) | O23: =L23-N23 | Q23: =IF(A23="","",IF(OR(L23<=0,C23="",D23="",F23=""),"需检查",IF(AND(C23="支出",I23="未收票"),"缺发票","正常")))
B24: =TEXT(A24,"yyyy-mm") | N24: =IFERROR(L24*M24/(1+M24),0) | O24: =L24-N24 | Q24: =IF(A24="","",IF(OR(L24<=0,C24="",D24="",F24=""),"需检查",IF(AND(C24="支出",I24="未收票"),"缺发票","正常")))
B25: =TEXT(A25,"yyyy-mm") | N25: =IFERROR(L25*M25/(1+M25),0) | O25: =L25-N25 | Q25: =IF(A25="","",IF(OR(L25<=0,C25="",D25="",F25=""),"需检查",IF(AND(C25="支出",I25="未收票"),"缺发票","正常")))
B26: =TEXT(A26,"yyyy-mm") | N26: =IFERROR(L26*M26/(1+M26),0) | O26: =L26-N26 | Q26: =IF(A26="","",IF(OR(L26<=0,C26="",D26="",F26=""),"需检查",IF(AND(C26="支出",I26="未收票"),"缺发票","正常")))
B27: =TEXT(A27,"yyyy-mm") | N27: =IFERROR(L27*M27/(1+M27),0) | O27: =L27-N27 | Q27: =IF(A27="","",IF(OR(L27<=0,C27="",D27="",F27=""),"需检查",IF(AND(C27="支出",I27="未收票"),"缺发票","正常")))
B28: =TEXT(A28,"yyyy-mm") | N28: =IFERROR(L28*M28/(1+M28),0) | O28: =L28-N28 | Q28: =IF(A28="","",IF(OR(L28<=0,C28="",D28="",F28=""),"需检查",IF(AND(C28="支出",I28="未收票"),"缺发票","正常")))
B29: =TEXT(A29,"yyyy-mm") | N29: =IFERROR(L29*M29/(1+M29),0) | O29: =L29-N29 | Q29: =IF(A29="","",IF(OR(L29<=0,C29="",D29="",F29=""),"需检查",IF(AND(C29="支出",I29="未收票"),"缺发票","正常")))
B30: =TEXT(A30,"yyyy-mm") | N30: =IFERROR(L30*M30/(1+M30),0) | O30: =L30-N30 | Q30: =IF(A30="","",IF(OR(L30<=0,C30="",D30="",F30=""),"需检查",IF(AND(C30="支出",I30="未收票"),"缺发票","正常")))
B31: =TEXT(A31,"yyyy-mm") | N31: =IFERROR(L31*M31/(1+M31),0) | O31: =L31-N31 | Q31: =IF(A31="","",IF(OR(L31<=0,C31="",D31="",F31=""),"需检查",IF(AND(C31="支出",I31="未收票"),"缺发票","正常")))
B32: =TEXT(A32,"yyyy-mm") | N32: =IFERROR(L32*M32/(1+M32),0) | O32: =L32-N32 | Q32: =IF(A32="","",IF(OR(L32<=0,C32="",D32="",F32=""),"需检查",IF(AND(C32="支出",I32="未收票"),"缺发票","正常")))
B33: =TEXT(A33,"yyyy-mm") | N33: =IFERROR(L33*M33/(1+M33),0) | O33: =L33-N33 | Q33: =IF(A33="","",IF(OR(L33<=0,C33="",D33="",F33=""),"需检查",IF(AND(C33="支出",I33="未收票"),"缺发票","正常")))
B34: =TEXT(A34,"yyyy-mm") | N34: =IFERROR(L34*M34/(1+M34),0) | O34: =L34-N34 | Q34: =IF(A34="","",IF(OR(L34<=0,C34="",D34="",F34=""),"需检查",IF(AND(C34="支出",I34="未收票"),"缺发票","正常")))
... B204: =TEXT(A204,"yyyy-mm") | N204: =IFERROR(L204*M204/(1+M204),0) | O204: =L204-N204 | Q204: =IF(A204="","",IF(OR(L204<=0,C204="",D204="",F204=""),"需检查",IF(AND(C204="支出",I204="未收票"),"缺发票","正常")))

Sheet 预算执行
A1: 年度预算执行表
A3: 黄色列为年度预算输入；各月实际取自“财务流水”中的支出数据。
A4: 部门 | B4: 费用类别 | C4: 年度预算 | D4: 1月实际 | E4: 2月实际 | F4: 3月实际 | G4: 4月实际 | H4: 5月实际 | I4: 6月实际 | J4: 7月实际 | K4: 8月实际 | L4: 9月实际 | M4: 10月实际 | N4: 11月实际 | O4: 12月实际 | P4: 累计实际 | Q4: 剩余预算 | R4: 执行率 | S4: 年度进度 | T4: 偏差状态 | U4: 责任人
A5: 运营部 | B5: 电费 | C5: 1200000 | D5: =SUMIFS(财务流水!$L$5:$L$204,财务流水!$B$5:$B$204,"2026-01",财务流水!$C$5:$C$204,"支出",财务流水!$D$5:$D$204,$A5,财务流水!$F$5:$F$204,$B5) | E5: =SUMIFS(财务流水!$L$5:$L$204,财务流水!$B$5:$B$204,"2026-02",财务流水!$C$5:$C$204,"支出",财务流水!$D$5:$D$204,$A5,财务流水!$F$5:$F$204,$B5) | F5: =SUMIFS(财务流水!$L$5:$L$204,财务流水!$B$5:$B$204,"2026-03",财务流水!$C$5:$C$204,"支出",财务流水!$D$5:$D$204,$A5,财务流水!$F$5:$F$204,$B5) | G5: =SUMIFS(财务流水!$L$5:$L$204,财务流水!$B$5:$B$204,"2026-04",财务流水!$C$5:$C$204,"支出",财务流水!$D$5:$D$204,$A5,财务流水!$F$5:$F$204,$B5) | H5: =SUMIFS(财务流水!$L$5:$L$204,财务流水!$B$5:$B$204,"2026-05",财务流水!$C$5:$C$204,"支出",财务流水!$D$5:$D$204,$A5,财务流水!$F$5:$F$204,$B5) | I5: =SUMIFS(财务流水!$L$5:$L$204,财务流水!$B$5:$B$204,"2026-06",财务流水!$C$5:$C$204,"支出",财务流水!$D$5:$D$204,$A5,财务流水!$F$5:$F$204,$B5) | J5: =SUMIFS(财务流水!$L$5:$L$204,财务流水!$B$5:$B$204,"2026-07",财务流水!$C$5:$C$204,"支出",财务流水!$D$5:$D$204,$A5,财务流水!$F$5:$F$204,$B5) | K5: =SUMIFS(财务流水!$L$5:$L$204,财务流水!$B$5:$B$204,"2026-08",财务流水!$C$5:$C$204,"支出",财务流水!$D$5:$D$204,$A5,财务流水!$F$5:$F$204,$B5) | L5: =SUMIFS(财务流水!$L$5:$L$204,财务流水!$B$5:$B$204,"2026-09",财务流水!$C$5:$C$204,"支出",财务流水!$D$5:$D$204,$A5,财务流水!$F$5:$F$204,$B5) | M5: =SUMIFS(财务流水!$L$5:$L$204,财务流水!$B$5:$B$204,"2026-10",财务流水!$C$5:$C$204,"支出",财务流水!$D$5:$D$204,$A5,财务流水!$F$5:$F$204,$B5) | N5: =SUMIFS(财务流水!$L$5:$L$204,财务流水!$B$5:$B$204,"2026-11",财务流水!$C$5:$C$204,"支出",财务流水!$D$5:$D$204,$A5,财务流水!$F$5:$F$204,$B5) | O5: =SUMIFS(财务流水!$L$5:$L$204,财务流水!$B$5:$B$204,"2026-12",财务流水!$C$5:$C$204,"支出",财务流水!$D$5:$D$204,$A5,财务流水!$F$5:$F$204,$B5) | P5: =SUM(D5:O5) | Q5: =C5-P5 | R5: =IFERROR(P5/C5,0) | S5: =7/12 | T5: =IF(R5>S5+10%,"超进度",IF(R5<S5-10%,"低于进度","正常")) | U5: 王芳
A6: 运营部 | B6: 运维费 | C6: 480000 | D6: =SUMIFS(财务流水!$L$5:$L$204,财务流水!$B$5:$B$204,"2026-01",财务流水!$C$5:$C$204,"支出",财务流水!$D$5:$D$204,$A6,财务流水!$F$5:$F$204,$B6) | E6: =SUMIFS(财务流水!$L$5:$L$204,财务流水!$B$5:$B$204,"2026-02",财务流水!$C$5:$C$204,"支出",财务流水!$D$5:$D$204,$A6,财务流水!$F$5:$F$204,$B6) | F6: =SUMIFS(财务流水!$L$5:$L$204,财务流水!$B$5:$B$204,"2026-03",财务流水!$C$5:$C$204,"支出",财务流水!$D$5:$D$204,$A6,财务流水!$F$5:$F$204,$B6) | G6: =SUMIFS(财务流水!$L$5:$L$204,财务流水!$B$5:$B$204,"2026-04",财务流水!$C$5:$C$204,"支出",财务流水!$D$5:$D$204,$A6,财务流水!$F$5:$F$204,$B6) | H6: =SUMIFS(财务流水!$L$5:$L$204,财务流水!$B$5:$B$204,"2026-05",财务流水!$C$5:$C$204,"支出",财务流水!$D$5:$D$204,$A6,财务流水!$F$5:$F$204,$B6) | I6: =SUMIFS(财务流水!$L$5:$L$204,财务流水!$B$5:$B$204,"2026-06",财务流水!$C$5:$C$204,"支出",财务流水!$D$5:$D$204,$A6,财务流水!$F$5:$F$204,$B6) | J6: =SUMIFS(财务流水!$L$5:$L$204,财务流水!$B$5:$B$204,"2026-07",财务流水!$C$5:$C$204,"支出",财务流水!$D$5:$D$204,$A6,财务流水!$F$5:$F$204,$B6) | K6: =SUMIFS(财务流水!$L$5:$L$204,财务流水!$B$5:$B$204,"2026-08",财务流水!$C$5:$C$204,"支出",财务流水!$D$5:$D$204,$A6,财务流水!$F$5:$F$204,$B6) | L6: =SUMIFS(财务流水!$L$5:$L$204,财务流水!$B$5:$B$204,"2026-09",财务流水!$C$5:$C$204,"支出",财务流水!$D$5:$D$204,$A6,财务流水!$F$5:$F$204,$B6) | M6: =SUMIFS(财务流水!$L$5:$L$204,财务流水!$B$5:$B$204,"2026-10",财务流水!$C$5:$C$204,"支出",财务流水!$D$5:$D$204,$A6,财务流水!$F$5:$F$204,$B6) | N6: =SUMIFS(财务流水!$L$5:$L$204,财务流水!$B$5:$B$204,"2026-11",财务流水!$C$5:$C$204,"支出",财务流水!$D$5:$D$204,$A6,财务流水!$F$5:$F$204,$B6) | O6: =SUMIFS(财务流水!$L$5:$L$204,财务流水!$B$5:$B$204,"2026-12",财务流水!$C$5:$C$204,"支出",财务流水!$D$5:$D$204,$A6,财务流水!$F$5:$F$204,$B6) | P6: =SUM(D6:O6) | Q6: =C6-P6 | R6: =IFERROR(P6/C6,0) | S6: =7/12 | T6: =IF(R6>S6+10%,"超进度",IF(R6<S6-10%,"低于进度","正常")) | U6: 王芳
A7: 研发部 | B7: 软件服务费 | C7: 600000 | D7: =SUMIFS(财务流水!$L$5:$L$204,财务流水!$B$5:$B$204,"2026-01",财务流水!$C$5:$C$204,"支出",财务流水!$D$5:$D$204,$A7,财务流水!$F$5:$F$204,$B7) | E7: =SUMIFS(财务流水!$L$5:$L$204,财务流水!$B$5:$B$204,"2026-02",财务流水!$C$5:$C$204,"支出",财务流水!$D$5:$D$204,$A7,财务流水!$F$5:$F$204,$B7) | F7: =SUMIFS(财务流水!$L$5:$L$204,财务流水!$B$5:$B$204,"2026-03",财务流水!$C$5:$C$204,"支出",财务流水!$D$5:$D$204,$A7,财务流水!$F$5:$F$204,$B7) | G7: =SUMIFS(财务流水!$L$5:$L$204,财务流水!$B$5:$B$204,"2026-04",财务流水!$C$5:$C$204,"支出",财务流水!$D$5:$D$204,$A7,财务流水!$F$5:$F$204,$B7) | H7: =SUMIFS(财务流水!$L$5:$L$204,财务流水!$B$5:$B$204,"2026-05",财务流水!$C$5:$C$204,"支出",财务流水!$D$5:$D$204,$A7,财务流水!$F$5:$F$204,$B7) | I7: =SUMIFS(财务流水!$L$5:$L$204,财务流水!$B$5:$B$204,"2026-06",财务流水!$C$5:$C$204,"支出",财务流水!$D$5:$D$204,$A7,财务流水!$F$5:$F$204,$B7) | J7: =SUMIFS(财务流水!$L$5:$L$204,财务流水!$B$5:$B$204,"2026-07",财务流水!$C$5:$C$204,"支出",财务流水!$D$5:$D$204,$A7,财务流水!$F$5:$F$204,$B7) | K7: =SUMIFS(财务流水!$L$5:$L$204,财务流水!$B$5:$B$204,"2026-08",财务流水!$C$5:$C$204,"支出",财务流水!$D$5:$D$204,$A7,财务流水!$F$5:$F$204,$B7) | L7: =SUMIFS(财务流水!$L$5:$L$204,财务流水!$B$5:$B$204,"2026-09",财务流水!$C$5:$C$204,"支出",财务流水!$D$5:$D$204,$A7,财务流水!$F$5:$F$204,$B7) | M7: =SUMIFS(财务流水!$L$5:$L$204,财务流水!$B$5:$B$204,"2026-10",财务流水!$C$5:$C$204,"支出",财务流水!$D$5:$D$204,$A7,财务流水!$F$5:$F$204,$B7) | N7: =SUMIFS(财务流水!$L$5:$L$204,财务流水!$B$5:$B$204,"2026-11",财务流水!$C$5:$C$204,"支出",财务流水!$D$5:$D$204,$A7,财务流水!$F$5:$F$204,$B7) | O7: =SUMIFS(财务流水!$L$5:$L$204,财务流水!$B$5:$B$204,"2026-12",财务流水!$C$5:$C$204,"支出",财务流水!$D$5:$D$204,$A7,财务流水!$F$5:$F$204,$B7) | P7: =SUM(D7:O7) | Q7: =C7-P7 | R7: =IFERROR(P7/C7,0) | S7: =7/12 | T7: =IF(R7>S7+10%,"超进度",IF(R7<S7-10%,"低于进度","正常")) | U7: 李强
A8: 研发部 | B8: 差旅费 | C8: 120000 | D8: =SUMIFS(财务流水!$L$5:$L$204,财务流水!$B$5:$B$204,"2026-01",财务流水!$C$5:$C$204,"支出",财务流水!$D$5:$D$204,$A8,财务流水!$F$5:$F$204,$B8) | E8: =SUMIFS(财务流水!$L$5:$L$204,财务流水!$B$5:$B$204,"2026-02",财务流水!$C$5:$C$204,"支出",财务流水!$D$5:$D$204,$A8,财务流水!$F$5:$F$204,$B8) | F8: =SUMIFS(财务流水!$L$5:$L$204,财务流水!$B$5:$B$204,"2026-03",财务流水!$C$5:$C$204,"支出",财务流水!$D$5:$D$204,$A8,财务流水!$F$5:$F$204,$B8) | G8: =SUMIFS(财务流水!$L$5:$L$204,财务流水!$B$5:$B$204,"2026-04",财务流水!$C$5:$C$204,"支出",财务流水!$D$5:$D$204,$A8,财务流水!$F$5:$F$204,$B8) | H8: =SUMIFS(财务流水!$L$5:$L$204,财务流水!$B$5:$B$204,"2026-05",财务流水!$C$5:$C$204,"支出",财务流水!$D$5:$D$204,$A8,财务流水!$F$5:$F$204,$B8) | I8: =SUMIFS(财务流水!$L$5:$L$204,财务流水!$B$5:$B$204,"2026-06",财务流水!$C$5:$C$204,"支出",财务流水!$D$5:$D$204,$A8,财务流水!$F$5:$F$204,$B8) | J8: =SUMIFS(财务流水!$L$5:$L$204,财务流水!$B$5:$B$204,"2026-07",财务流水!$C$5:$C$204,"支出",财务流水!$D$5:$D$204,$A8,财务流水!$F$5:$F$204,$B8) | K8: =SUMIFS(财务流水!$L$5:$L$204,财务流水!$B$5:$B$204,"2026-08",财务流水!$C$5:$C$204,"支出",财务流水!$D$5:$D$204,$A8,财务流水!$F$5:$F$204,$B8) | L8: =SUMIFS(财务流水!$L$5:$L$204,财务流水!$B$5:$B$204,"2026-09",财务流水!$C$5:$C$204,"支出",财务流水!$D$5:$D$204,$A8,财务流水!$F$5:$F$204,$B8) | M8: =SUMIFS(财务流水!$L$5:$L$204,财务流水!$B$5:$B$204,"2026-10",财务流水!$C$5:$C$204,"支出",财务流水!$D$5:$D$204,$A8,财务流水!$F$5:$F$204,$B8) | N8: =SUMIFS(财务流水!$L$5:$L$204,财务流水!$B$5:$B$204,"2026-11",财务流水!$C$5:$C$204,"支出",财务流水!$D$5:$D$204,$A8,财务流水!$F$5:$F$204,$B8) | O8: =SUMIFS(财务流水!$L$5:$L$204,财务流水!$B$5:$B$204,"2026-12",财务流水!$C$5:$C$204,"支出",财务流水!$D$5:$D$204,$A8,财务流水!$F$5:$F$204,$B8) | P8: =SUM(D8:O8) | Q8: =C8-P8 | R8: =IFERROR(P8/C8,0) | S8: =7/12 | T8: =IF(R8>S8+10%,"超进度",IF(R8<S8-10%,"低于进度","正常")) | U8: 李强
A9: 项目部 | B9: 设备采购 | C9: 900000 | D9: =SUMIFS(财务流水!$L$5:$L$204,财务流水!$B$5:$B$204,"2026-01",财务流水!$C$5:$C$204,"支出",财务流水!$D$5:$D$204,$A9,财务流水!$F$5:$F$204,$B9) | E9: =SUMIFS(财务流水!$L$5:$L$204,财务流水!$B$5:$B$204,"2026-02",财务流水!$C$5:$C$204,"支出",财务流水!$D$5:$D$204,$A9,财务流水!$F$5:$F$204,$B9) | F9: =SUMIFS(财务流水!$L$5:$L$204,财务流水!$B$5:$B$204,"2026-03",财务流水!$C$5:$C$204,"支出",财务流水!$D$5:$D$204,$A9,财务流水!$F$5:$F$204,$B9) | G9: =SUMIFS(财务流水!$L$5:$L$204,财务流水!$B$5:$B$204,"2026-04",财务流水!$C$5:$C$204,"支出",财务流水!$D$5:$D$204,$A9,财务流水!$F$5:$F$204,$B9) | H9: =SUMIFS(财务流水!$L$5:$L$204,财务流水!$B$5:$B$204,"2026-05",财务流水!$C$5:$C$204,"支出",财务流水!$D$5:$D$204,$A9,财务流水!$F$5:$F$204,$B9) | I9: =SUMIFS(财务流水!$L$5:$L$204,财务流水!$B$5:$B$204,"2026-06",财务流水!$C$5:$C$204,"支出",财务流水!$D$5:$D$204,$A9,财务流水!$F$5:$F$204,$B9) | J9: =SUMIFS(财务流水!$L$5:$L$204,财务流水!$B$5:$B$204,"2026-07",财务流水!$C$5:$C$204,"支出",财务流水!$D$5:$D$204,$A9,财务流水!$F$5:$F$204,$B9) | K9: =SUMIFS(财务流水!$L$5:$L$204,财务流水!$B$5:$B$204,"2026-08",财务流水!$C$5:$C$204,"支出",财务流水!$D$5:$D$204,$A9,财务流水!$F$5:$F$204,$B9) | L9: =SUMIFS(财务流水!$L$5:$L$204,财务流水!$B$5:$B$204,"2026-09",财务流水!$C$5:$C$204,"支出",财务流水!$D$5:$D$204,$A9,财务流水!$F$5:$F$204,$B9) | M9: =SUMIFS(财务流水!$L$5:$L$204,财务流水!$B$5:$B$204,"2026-10",财务流水!$C$5:$C$204,"支出",财务流水!$D$5:$D$204,$A9,财务流水!$F$5:$F$204,$B9) | N9: =SUMIFS(财务流水!$L$5:$L$204,财务流水!$B$5:$B$204,"2026-11",财务流水!$C$5:$C$204,"支出",财务流水!$D$5:$D$204,$A9,财务流水!$F$5:$F$204,$B9) | O9: =SUMIFS(财务流水!$L$5:$L$204,财务流水!$B$5:$B$204,"2026-12",财务流水!$C$5:$C$204,"支出",财务流水!$D$5:$D$204,$A9,财务流水!$F$5:$F$204,$B9) | P9: =SUM(D9:O9) | Q9: =C9-P9 | R9: =IFERROR(P9/C9,0) | S9: =7/12 | T9: =IF(R9>S9+10%,"超进度",IF(R9<S9-10%,"低于进度","正常")) | U9: 陈杰
A10: 市场部 | B10: 市场推广费 | C10: 360000 | D10: =SUMIFS(财务流水!$L$5:$L$204,财务流水!$B$5:$B$204,"2026-01",财务流水!$C$5:$C$204,"支出",财务流水!$D$5:$D$204,$A10,财务流水!$F$5:$F$204,$B10) | E10: =SUMIFS(财务流水!$L$5:$L$204,财务流水!$B$5:$B$204,"2026-02",财务流水!$C$5:$C$204,"支出",财务流水!$D$5:$D$204,$A10,财务流水!$F$5:$F$204,$B10) | F10: =SUMIFS(财务流水!$L$5:$L$204,财务流水!$B$5:$B$204,"2026-03",财务流水!$C$5:$C$204,"支出",财务流水!$D$5:$D$204,$A10,财务流水!$F$5:$F$204,$B10) | G10: =SUMIFS(财务流水!$L$5:$L$204,财务流水!$B$5:$B$204,"2026-04",财务流水!$C$5:$C$204,"支出",财务流水!$D$5:$D$204,$A10,财务流水!$F$5:$F$204,$B10) | H10: =SUMIFS(财务流水!$L$5:$L$204,财务流水!$B$5:$B$204,"2026-05",财务流水!$C$5:$C$204,"支出",财务流水!$D$5:$D$204,$A10,财务流水!$F$5:$F$204,$B10) | I10: =SUMIFS(财务流水!$L$5:$L$204,财务流水!$B$5:$B$204,"2026-06",财务流水!$C$5:$C$204,"支出",财务流水!$D$5:$D$204,$A10,财务流水!$F$5:$F$204,$B10) | J10: =SUMIFS(财务流水!$L$5:$L$204,财务流水!$B$5:$B$204,"2026-07",财务流水!$C$5:$C$204,"支出",财务流水!$D$5:$D$204,$A10,财务流水!$F$5:$F$204,$B10) | K10: =SUMIFS(财务流水!$L$5:$L$204,财务流水!$B$5:$B$204,"2026-08",财务流水!$C$5:$C$204,"支出",财务流水!$D$5:$D$204,$A10,财务流水!$F$5:$F$204,$B10) | L10: =SUMIFS(财务流水!$L$5:$L$204,财务流水!$B$5:$B$204,"2026-09",财务流水!$C$5:$C$204,"支出",财务流水!$D$5:$D$204,$A10,财务流水!$F$5:$F$204,$B10) | M10: =SUMIFS(财务流水!$L$5:$L$204,财务流水!$B$5:$B$204,"2026-10",财务流水!$C$5:$C$204,"支出",财务流水!$D$5:$D$204,$A10,财务流水!$F$5:$F$204,$B10) | N10: =SUMIFS(财务流水!$L$5:$L$204,财务流水!$B$5:$B$204,"2026-11",财务流水!$C$5:$C$204,"支出",财务流水!$D$5:$D$204,$A10,财务流水!$F$5:$F$204,$B10) | O10: =SUMIFS(财务流水!$L$5:$L$204,财务流水!$B$5:$B$204,"2026-12",财务流水!$C$5:$C$204,"支出",财务流水!$D$5:$D$204,$A10,财务流水!$F$5:$F$204,$B10) | P10: =SUM(D10:O10) | Q10: =C10-P10 | R10: =IFERROR(P10/C10,0) | S10: =7/12 | T10: =IF(R10>S10+10%,"超进度",IF(R10<S10-10%,"低于进度","正常")) | U10: 赵晨
A11: 行政部 | B11: 办公费 | C11: 180000 | D11: =SUMIFS(财务流水!$L$5:$L$204,财务流水!$B$5:$B$204,"2026-01",财务流水!$C$5:$C$204,"支出",财务流水!$D$5:$D$204,$A11,财务流水!$F$5:$F$204,$B11) | E11: =SUMIFS(财务流水!$L$5:$L$204,财务流水!$B$5:$B$204,"2026-02",财务流水!$C$5:$C$204,"支出",财务流水!$D$5:$D$204,$A11,财务流水!$F$5:$F$204,$B11) | F11: =SUMIFS(财务流水!$L$5:$L$204,财务流水!$B$5:$B$204,"2026-03",财务流水!$C$5:$C$204,"支出",财务流水!$D$5:$D$204,$A11,财务流水!$F$5:$F$204,$B11) | G11: =SUMIFS(财务流水!$L$5:$L$204,财务流水!$B$5:$B$204,"2026-04",财务流水!$C$5:$C$204,"支出",财务流水!$D$5:$D$204,$A11,财务流水!$F$5:$F$204,$B11) | H11: =SUMIFS(财务流水!$L$5:$L$204,财务流水!$B$5:$B$204,"2026-05",财务流水!$C$5:$C$204,"支出",财务流水!$D$5:$D$204,$A11,财务流水!$F$5:$F$204,$B11) | I11: =SUMIFS(财务流水!$L$5:$L$204,财务流水!$B$5:$B$204,"2026-06",财务流水!$C$5:$C$204,"支出",财务流水!$D$5:$D$204,$A11,财务流水!$F$5:$F$204,$B11) | J11: =SUMIFS(财务流水!$L$5:$L$204,财务流水!$B$5:$B$204,"2026-07",财务流水!$C$5:$C$204,"支出",财务流水!$D$5:$D$204,$A11,财务流水!$F$5:$F$204,$B11) | K11: =SUMIFS(财务流水!$L$5:$L$204,财务流水!$B$5:$B$204,"2026-08",财务流水!$C$5:$C$204,"支出",财务流水!$D$5:$D$204,$A11,财务流水!$F$5:$F$204,$B11) | L11: =SUMIFS(财务流水!$L$5:$L$204,财务流水!$B$5:$B$204,"2026-09",财务流水!$C$5:$C$204,"支出",财务流水!$D$5:$D$204,$A11,财务流水!$F$5:$F$204,$B11) | M11: =SUMIFS(财务流水!$L$5:$L$204,财务流水!$B$5:$B$204,"2026-10",财务流水!$C$5:$C$204,"支出",财务流水!$D$5:$D$204,$A11,财务流水!$F$5:$F$204,$B11) | N11: =SUMIFS(财务流水!$L$5:$L$204,财务流水!$B$5:$B$204,"2026-11",财务流水!$C$5:$C$204,"支出",财务流水!$D$5:$D$204,$A11,财务流水!$F$5:$F$204,$B11) | O11: =SUMIFS(财务流水!$L$5:$L$204,财务流水!$B$5:$B$204,"2026-12",财务流水!$C$5:$C$204,"支出",财务流水!$D$5:$D$204,$A11,财务流水!$F$5:$F$204,$B11) | P11: =SUM(D11:O11) | Q11: =C11-P11 | R11: =IFERROR(P11/C11,0) | S11: =7/12 | T11: =IF(R11>S11+10%,"超进度",IF(R11<S11-10%,"低于进度","正常")) | U11: 刘悦
A12: 人力资源部 | B12: 培训费 | C12: 240000 | D12: =SUMIFS(财务流水!$L$5:$L$204,财务流水!$B$5:$B$204,"2026-01",财务流水!$C$5:$C$204,"支出",财务流水!$D$5:$D$204,$A12,财务流水!$F$5:$F$204,$B12) | E12: =SUMIFS(财务流水!$L$5:$L$204,财务流水!$B$5:$B$204,"2026-02",财务流水!$C$5:$C$204,"支出",财务流水!$D$5:$D$204,$A12,财务流水!$F$5:$F$204,$B12) | F12: =SUMIFS(财务流水!$L$5:$L$204,财务流水!$B$5:$B$204,"2026-03",财务流水!$C$5:$C$204,"支出",财务流水!$D$5:$D$204,$A12,财务流水!$F$5:$F$204,$B12) | G12: =SUMIFS(财务流水!$L$5:$L$204,财务流水!$B$5:$B$204,"2026-04",财务流水!$C$5:$C$204,"支出",财务流水!$D$5:$D$204,$A12,财务流水!$F$5:$F$204,$B12) | H12: =SUMIFS(财务流水!$L$5:$L$204,财务流水!$B$5:$B$204,"2026-05",财务流水!$C$5:$C$204,"支出",财务流水!$D$5:$D$204,$A12,财务流水!$F$5:$F$204,$B12) | I12: =SUMIFS(财务流水!$L$5:$L$204,财务流水!$B$5:$B$204,"2026-06",财务流水!$C$5:$C$204,"支出",财务流水!$D$5:$D$204,$A12,财务流水!$F$5:$F$204,$B12) | J12: =SUMIFS(财务流水!$L$5:$L$204,财务流水!$B$5:$B$204,"2026-07",财务流水!$C$5:$C$204,"支出",财务流水!$D$5:$D$204,$A12,财务流水!$F$5:$F$204,$B12) | K12: =SUMIFS(财务流水!$L$5:$L$204,财务流水!$B$5:$B$204,"2026-08",财务流水!$C$5:$C$204,"支出",财务流水!$D$5:$D$204,$A12,财务流水!$F$5:$F$204,$B12) | L12: =SUMIFS(财务流水!$L$5:$L$204,财务流水!$B$5:$B$204,"2026-09",财务流水!$C$5:$C$204,"支出",财务流水!$D$5:$D$204,$A12,财务流水!$F$5:$F$204,$B12) | M12: =SUMIFS(财务流水!$L$5:$L$204,财务流水!$B$5:$B$204,"2026-10",财务流水!$C$5:$C$204,"支出",财务流水!$D$5:$D$204,$A12,财务流水!$F$5:$F$204,$B12) | N12: =SUMIFS(财务流水!$L$5:$L$204,财务流水!$B$5:$B$204,"2026-11",财务流水!$C$5:$C$204,"支出",财务流水!$D$5:$D$204,$A12,财务流水!$F$5:$F$204,$B12) | O12: =SUMIFS(财务流水!$L$5:$L$204,财务流水!$B$5:$B$204,"2026-12",财务流水!$C$5:$C$204,"支出",财务流水!$D$5:$D$204,$A12,财务流水!$F$5:$F$204,$B12) | P12: =SUM(D12:O12) | Q12: =C12-P12 | R12: =IFERROR(P12/C12,0) | S12: =7/12 | T12: =IF(R12>S12+10%,"超进度",IF(R12<S12-10%,"低于进度","正常")) | U12: 孙静
A13: 合计 | C13: =SUM(C5:C12) | D13: =SUM(D5:D12) | E13: =SUM(E5:E12) | F13: =SUM(F5:F12) | G13: =SUM(G5:G12) | H13: =SUM(H5:H12) | I13: =SUM(I5:I12) | J13: =SUM(J5:J12) | ... Q13: =SUM(Q5:Q12) | R13: =IFERROR(P13/C13,0) | S13: =7/12 | T13: =IF(R13>S13+10%,"超进度",IF(R13<S13-10%,"低于进度","正常"))

Sheet 应收应付
A1: 应收应付与账期跟踪
A3: 单号 | B3: 类型 | C3: 对方单位 | D3: 项目 | E3: 合同金额 | F3: 已收/已付 | G3: 未结金额 | H3: 到期日 | I3: 状态 | J3: 逾期天数 | K3: 负责人 | L3: 下一步动作
A4: AR-26001 | B4: 应收 | C4: 某能源公司 | D4: 储能改造项目 | E4: 420000 | F4: 200000 | G4: =E4-F4 | H4: 46203 | I4: =IF(A4="","",IF(G4<=0,"已结清",IF(H4<TODAY(),"已逾期","未到期"))) | J4: =IF(OR(A4="",G4<=0),0,MAX(0,TODAY()-H4)) | K4: 陈杰 | L4: 催收剩余里程碑款
A5: AR-26002 | B5: 应收 | C5: 某电力公司 | D5: 数据平台项目 | E5: 780000 | F5: 560000 | G5: =E5-F5 | H5: 46223 | I5: =IF(A5="","",IF(G5<=0,"已结清",IF(H5<TODAY(),"已逾期","未到期"))) | J5: =IF(OR(A5="",G5<=0),0,MAX(0,TODAY()-H5)) | K5: 陈杰 | L5: 验收后开票催收
A6: AR-26003 | B6: 应收 | C6: 常州某运营公司 | D6: 7月充电服务 | E6: 335000 | F6: 335000 | G6: =E6-F6 | H6: 46213 | I6: =IF(A6="","",IF(G6<=0,"已结清",IF(H6<TODAY(),"已逾期","未到期"))) | J6: =IF(OR(A6="",G6<=0),0,MAX(0,TODAY()-H6)) | K6: 张敏 | L6: 已结清归档
A7: AP-26001 | B7: 应付 | C7: 某科技公司 | D7: AI平台API费用 | E7: 42000 | F7: 0 | G7: =E7-F7 | H7: 46234 | I7: =IF(A7="","",IF(G7<=0,"已结清",IF(H7<TODAY(),"已逾期","未到期"))) | J7: =IF(OR(A7="",G7<=0),0,MAX(0,TODAY()-H7)) | K7: 李强 | L7: 核对发票后付款
A8: AP-26002 | B8: 应付 | C8: 某传媒公司 | D8: 品牌内容制作 | E8: 18000 | F8: 0 | G8: =E8-F8 | H8: 46228 | I8: =IF(A8="","",IF(G8<=0,"已结清",IF(H8<TODAY(),"已逾期","未到期"))) | J8: =IF(OR(A8="",G8<=0),0,MAX(0,TODAY()-H8)) | K8: 赵晨 | L8: 补齐发票与验收材料
A9: AP-26003 | B9: 应付 | C9: 某运维公司 | D9: 凤凰谷年度巡检 | E9: 46000 | F9: 0 | G9: =E9-F9 | H9: 46188 | I9: =IF(A9="","",IF(G9<=0,"已结清",IF(H9<TODAY(),"已逾期","未到期"))) | J9: =IF(OR(A9="",G9<=0),0,MAX(0,TODAY()-H9)) | K9: 王芳 | L9: 确认巡检报告并排款
G10: =E10-F10 | I10: =IF(A10="","",IF(G10<=0,"已结清",IF(H10<TODAY(),"已逾期","未到期"))) | J10: =IF(OR(A10="",G10<=0),0,MAX(0,TODAY()-H10))
G11: =E11-F11 | I11: =IF(A11="","",IF(G11<=0,"已结清",IF(H11<TODAY(),"已逾期","未到期"))) | J11: =IF(OR(A11="",G11<=0),0,MAX(0,TODAY()-H11))
G12: =E12-F12 | I12: =IF(A12="","",IF(G12<=0,"已结清",IF(H12<TODAY(),"已逾期","未到期"))) | J12: =IF(OR(A12="",G12<=0),0,MAX(0,TODAY()-H12))
G13: =E13-F13 | I13: =IF(A13="","",IF(G13<=0,"已结清",IF(H13<TODAY(),"已逾期","未到期"))) | J13: =IF(OR(A13="",G13<=0),0,MAX(0,TODAY()-H13))
G14: =E14-F14 | I14: =IF(A14="","",IF(G14<=0,"已结清",IF(H14<TODAY(),"已逾期","未到期"))) | J14: =IF(OR(A14="",G14<=0),0,MAX(0,TODAY()-H14))
G15: =E15-F15 | I15: =IF(A15="","",IF(G15<=0,"已结清",IF(H15<TODAY(),"已逾期","未到期"))) | J15: =IF(OR(A15="",G15<=0),0,MAX(0,TODAY()-H15))
G16: =E16-F16 | I16: =IF(A16="","",IF(G16<=0,"已结清",IF(H16<TODAY(),"已逾期","未到期"))) | J16: =IF(OR(A16="",G16<=0),0,MAX(0,TODAY()-H16))
G17: =E17-F17 | I17: =IF(A17="","",IF(G17<=0,"已结清",IF(H17<TODAY(),"已逾期","未到期"))) | J17: =IF(OR(A17="",G17<=0),0,MAX(0,TODAY()-H17))
G18: =E18-F18 | I18: =IF(A18="","",IF(G18<=0,"已结清",IF(H18<TODAY(),"已逾期","未到期"))) | J18: =IF(OR(A18="",G18<=0),0,MAX(0,TODAY()-H18))
G19: =E19-F19 | I19: =IF(A19="","",IF(G19<=0,"已结清",IF(H19<TODAY(),"已逾期","未到期"))) | J19: =IF(OR(A19="",G19<=0),0,MAX(0,TODAY()-H19))
G20: =E20-F20 | I20: =IF(A20="","",IF(G20<=0,"已结清",IF(H20<TODAY(),"已逾期","未到期"))) | J20: =IF(OR(A20="",G20<=0),0,MAX(0,TODAY()-H20))
G21: =E21-F21 | I21: =IF(A21="","",IF(G21<=0,"已结清",IF(H21<TODAY(),"已逾期","未到期"))) | J21: =IF(OR(A21="",G21<=0),0,MAX(0,TODAY()-H21))
... G103: =E103-F103 | I103: =IF(A103="","",IF(G103<=0,"已结清",IF(H103<TODAY(),"已逾期","未到期"))) | J103: =IF(OR(A103="",G103<=0),0,MAX(0,TODAY()-H103))

Sheet 月度汇总
A1: 2026年月度经营财务汇总
A4: 月份 | B4: 收入 | C4: 支出 | D4: 净现金流 | E4: 累计净现金流 | F4: 支出预算 | G4: 预算差异 | H4: 预算执行率
A5: 2026-01 | B5: =SUMIFS(财务流水!$L$5:$L$204,财务流水!$B$5:$B$204,A5,财务流水!$C$5:$C$204,"收入") | C5: =SUMIFS(财务流水!$L$5:$L$204,财务流水!$B$5:$B$204,A5,财务流水!$C$5:$C$204,"支出") | D5: =B5-C5 | E5: =D5 | F5: =预算执行!$C$13/12 | G5: =F5-C5 | H5: =IFERROR(C5/F5,0)
A6: 2026-02 | B6: =SUMIFS(财务流水!$L$5:$L$204,财务流水!$B$5:$B$204,A6,财务流水!$C$5:$C$204,"收入") | C6: =SUMIFS(财务流水!$L$5:$L$204,财务流水!$B$5:$B$204,A6,财务流水!$C$5:$C$204,"支出") | D6: =B6-C6 | E6: =E5+D6 | F6: =预算执行!$C$13/12 | G6: =F6-C6 | H6: =IFERROR(C6/F6,0)
A7: 2026-03 | B7: =SUMIFS(财务流水!$L$5:$L$204,财务流水!$B$5:$B$204,A7,财务流水!$C$5:$C$204,"收入") | C7: =SUMIFS(财务流水!$L$5:$L$204,财务流水!$B$5:$B$204,A7,财务流水!$C$5:$C$204,"支出") | D7: =B7-C7 | E7: =E6+D7 | F7: =预算执行!$C$13/12 | G7: =F7-C7 | H7: =IFERROR(C7/F7,0)
A8: 2026-04 | B8: =SUMIFS(财务流水!$L$5:$L$204,财务流水!$B$5:$B$204,A8,财务流水!$C$5:$C$204,"收入") | C8: =SUMIFS(财务流水!$L$5:$L$204,财务流水!$B$5:$B$204,A8,财务流水!$C$5:$C$204,"支出") | D8: =B8-C8 | E8: =E7+D8 | F8: =预算执行!$C$13/12 | G8: =F8-C8 | H8: =IFERROR(C8/F8,0)
A9: 2026-05 | B9: =SUMIFS(财务流水!$L$5:$L$204,财务流水!$B$5:$B$204,A9,财务流水!$C$5:$C$204,"收入") | C9: =SUMIFS(财务流水!$L$5:$L$204,财务流水!$B$5:$B$204,A9,财务流水!$C$5:$C$204,"支出") | D9: =B9-C9 | E9: =E8+D9 | F9: =预算执行!$C$13/12 | G9: =F9-C9 | H9: =IFERROR(C9/F9,0)
A10: 2026-06 | B10: =SUMIFS(财务流水!$L$5:$L$204,财务流水!$B$5:$B$204,A10,财务流水!$C$5:$C$204,"收入") | C10: =SUMIFS(财务流水!$L$5:$L$204,财务流水!$B$5:$B$204,A10,财务流水!$C$5:$C$204,"支出") | D10: =B10-C10 | E10: =E9+D10 | F10: =预算执行!$C$13/12 | G10: =F10-C10 | H10: =IFERROR(C10/F10,0)
A11: 2026-07 | B11: =SUMIFS(财务流水!$L$5:$L$204,财务流水!$B$5:$B$204,A11,财务流水!$C$5:$C$204,"收入") | C11: =SUMIFS(财务流水!$L$5:$L$204,财务流水!$B$5:$B$204,A11,财务流水!$C$5:$C$204,"支出") | D11: =B11-C11 | E11: =E10+D11 | F11: =预算执行!$C$13/12 | G11: =F11-C11 | H11: =IFERROR(C11/F11,0)
A12: 2026-08 | B12: =SUMIFS(财务流水!$L$5:$L$204,财务流水!$B$5:$B$204,A12,财务流水!$C$5:$C$204,"收入") | C12: =SUMIFS(财务流水!$L$5:$L$204,财务流水!$B$5:$B$204,A12,财务流水!$C$5:$C$204,"支出") | D12: =B12-C12 | E12: =E11+D12 | F12: =预算执行!$C$13/12 | G12: =F12-C12 | H12: =IFERROR(C12/F12,0)
A13: 2026-09 | B13: =SUMIFS(财务流水!$L$5:$L$204,财务流水!$B$5:$B$204,A13,财务流水!$C$5:$C$204,"收入") | C13: =SUMIFS(财务流水!$L$5:$L$204,财务流水!$B$5:$B$204,A13,财务流水!$C$5:$C$204,"支出") | D13: =B13-C13 | E13: =E12+D13 | F13: =预算执行!$C$13/12 | G13: =F13-C13 | H13: =IFERROR(C13/F13,0)
A14: 2026-10 | B14: =SUMIFS(财务流水!$L$5:$L$204,财务流水!$B$5:$B$204,A14,财务流水!$C$5:$C$204,"收入") | C14: =SUMIFS(财务流水!$L$5:$L$204,财务流水!$B$5:$B$204,A14,财务流水!$C$5:$C$204,"支出") | D14: =B14-C14 | E14: =E13+D14 | F14: =预算执行!$C$13/12 | G14: =F14-C14 | H14: =IFERROR(C14/F14,0)
A15: 2026-11 | B15: =SUMIFS(财务流水!$L$5:$L$204,财务流水!$B$5:$B$204,A15,财务流水!$C$5:$C$204,"收入") | C15: =SUMIFS(财务流水!$L$5:$L$204,财务流水!$B$5:$B$204,A15,财务流水!$C$5:$C$204,"支出") | D15: =B15-C15 | E15: =E14+D15 | F15: =预算执行!$C$13/12 | G15: =F15-C15 | H15: =IFERROR(C15/F15,0)
A16: 2026-12 | B16: =SUMIFS(财务流水!$L$5:$L$204,财务流水!$B$5:$B$204,A16,财务流水!$C$5:$C$204,"收入") | C16: =SUMIFS(财务流水!$L$5:$L$204,财务流水!$B$5:$B$204,A16,财务流水!$C$5:$C$204,"支出") | D16: =B16-C16 | E16: =E15+D16 | F16: =预算执行!$C$13/12 | G16: =F16-C16 | H16: =IFERROR(C16/F16,0)
A17: 全年合计 | B17: =SUM(B5:B16) | C17: =SUM(C5:C16) | D17: =SUM(D5:D16) | E17: =E16 | F17: =SUM(F5:F16) | G17: =SUM(G5:G16) | H17: =IFERROR(C17/F17,0)

Sheet 管理看板
A1: 财务管理看板
A3: 查看月份 | B3: 2026-07
A5: 本月收入 | D5: 本月支出 | G5: 净现金流 | J5: 逾期未结
A6: =SUMIFS(财务流水!$L$5:$L$204,财务流水!$B$5:$B$204,$B$3,财务流水!$C$5:$C$204,"收入") | D6: =SUMIFS(财务流水!$L$5:$L$204,财务流水!$B$5:$B$204,$B$3,财务流水!$C$5:$C$204,"支出") | G6: =A6-D6 | J6: =SUMIFS(应收应付!$G$4:$G$103,应收应付!$I$4:$I$103,"已逾期")
A8: 本月费用结构
A9: 费用类别 | B9: 金额
A10: 电费 | B10: =SUMIFS(财务流水!$L$5:$L$204,财务流水!$B$5:$B$204,$B$3,财务流水!$C$5:$C$204,"支出",财务流水!$F$5:$F$204,A10)
A11: 运维费 | B11: =SUMIFS(财务流水!$L$5:$L$204,财务流水!$B$5:$B$204,$B$3,财务流水!$C$5:$C$204,"支出",财务流水!$F$5:$F$204,A11)
A12: 软件服务费 | B12: =SUMIFS(财务流水!$L$5:$L$204,财务流水!$B$5:$B$204,$B$3,财务流水!$C$5:$C$204,"支出",财务流水!$F$5:$F$204,A12)
A13: 差旅费 | B13: =SUMIFS(财务流水!$L$5:$L$204,财务流水!$B$5:$B$204,$B$3,财务流水!$C$5:$C$204,"支出",财务流水!$F$5:$F$204,A13)
A14: 设备采购 | B14: =SUMIFS(财务流水!$L$5:$L$204,财务流水!$B$5:$B$204,$B$3,财务流水!$C$5:$C$204,"支出",财务流水!$F$5:$F$204,A14)
A15: 市场推广费 | B15: =SUMIFS(财务流水!$L$5:$L$204,财务流水!$B$5:$B$204,$B$3,财务流水!$C$5:$C$204,"支出",财务流水!$F$5:$F$204,A15)
A16: 办公费 | B16: =SUMIFS(财务流水!$L$5:$L$204,财务流水!$B$5:$B$204,$B$3,财务流水!$C$5:$C$204,"支出",财务流水!$F$5:$F$204,A16)
A17: 培训费 | B17: =SUMIFS(财务流水!$L$5:$L$204,财务流水!$B$5:$B$204,$B$3,财务流水!$C$5:$C$204,"支出",财务流水!$F$5:$F$204,A17)
A20: 管理提示
A21: =IF(J6>0,"存在逾期未结款项，请优先核对“应收应付”工作表。",IF(D6>A6,"本月支出高于收入，请关注现金流与预算执行。","本月现金流为正，继续跟踪未开票和未付款事项。"))
G22: 月份 | H22: 净现金流
G23: =月度汇总!A5 | H23: =月度汇总!D5
G24: =月度汇总!A6 | H24: =月度汇总!D6
G25: =月度汇总!A7 | H25: =月度汇总!D7
G26: =月度汇总!A8 | H26: =月度汇总!D8
G27: =月度汇总!A9 | H27: =月度汇总!D9
G28: =月度汇总!A10 | H28: =月度汇总!D10
G29: =月度汇总!A11 | H29: =月度汇总!D11
G30: =月度汇总!A12 | H30: =月度汇总!D12
G31: =月度汇总!A13 | H31: =月度汇总!D13
G32: =月度汇总!A14 | H32: =月度汇总!D14
G33: =月度汇总!A15 | H33: =月度汇总!D15
G34: =月度汇总!A16 | H34: =月度汇总!D16

Sheet 公式溯源
A1: 2026年7月报表 — 汇总数字来源与计算公式溯源表
A2: 说明：所有金额单位为人民币元，保留两位小数；“数值”列为本 Agent 按“计算公式”独立复算结果，与原模板公式口径一致。
A3: 汇总项 | B3: 数值(元) | C3: 来源工作表 | D3: 来源字段/单元格 | E3: 计算公式 | F3: 备注
A4: 【本月收入】
A5: 本月收入合计(含税) | B5: 555000 | C5: 财务流水 | D5: 列L金额(含税)；列C业务类型=收入；列B月份=2026-07 | E5: =SUMIFS(财务流水!L:L, 月份,"2026-07", 业务类型,"收入") | F5: r18 充电服务收入335000 + r22 项目服务收入220000
A6: — 充电服务收入(金坛体育馆站) | B6: 335000 | C6: 财务流水!L18 | D6: 金额(含税)=335000 | E6: 逐笔取值(运营部/金坛体育馆站) | F6: 已开票/已收款
A7: — 项目服务收入(数据平台项目) | B7: 220000 | C7: 财务流水!L22 | D7: 金额(含税)=220000 | E7: 逐笔取值(项目部/数据平台项目) | F7: 待财务复核：未开票/未收款，未形成现金流入
A8: 【本月支出】
A9: 本月支出合计(含税) | B9: 168000 | C9: 财务流水 | D9: 列L金额(含税)；列C业务类型=支出；列B月份=2026-07 | E9: =SUMIFS(财务流水!L:L, 月份,"2026-07", 业务类型,"支出") | F9: r19 电费108000 + r20 软件服务费42000 + r21 市场推广费18000
A10: — 电费(运营部/金坛体育馆站) | B10: 108000 | C10: 财务流水!L19 | D10: 金额(含税)=108000 | E10: 逐笔取值 | F10: 已收票/已付款
A11: — 软件服务费(研发部/AI平台一期) | B11: 42000 | C11: 财务流水!L20 | D11: 金额(含税)=42000 | E11: 逐笔取值 | F11: 已收票/未付款(到期2026-07-31)
A12: — 市场推广费(市场部/品牌推广) | B12: 18000 | C12: 财务流水!L21 | D12: 金额(含税)=18000 | E12: 逐笔取值 | F12: 待财务复核：未收票(缺发票)/未付款
A13: 【净现金流】
A14: 本月净现金流 | B14: 387000 | C14: 月度汇总!D11 | D14: 本月收入-本月支出 | E14: =SUMIFS(收入,"2026-07")-SUMIFS(支出,"2026-07") = 555000-168000 | F14: 模板口径为含税全额(权责发生)，含未收款/未付款；非纯现金口径
A15: 【应收账款】
A16: 应收账款未结合计 | B16: 440000 | C16: 应收应付 | D16: 列G未结金额；列B类型=应收 | E16: =SUMIFS(应收应付!G:G, 类型,"应收") | F16: AR-26001 未结220000(已逾期19天) + AR-26002 未结220000(未到期)；AR-26003 已结清
A17: 应付账款未结合计 | B17: 106000 | C17: 应收应付 | D17: 列G未结金额；列B类型=应付 | E17: =SUMIFS(应收应付!G:G, 类型,"应付") | F17: AP-26001 42000 + AP-26002 18000 + AP-26003 46000(已逾期34天)
A18: 逾期未结合计(应收+应付) | B18: 266000 | C18: 管理看板!J6 | D18: 列G未结金额；列I状态=已逾期 | E18: =SUMIFS(应收应付!G:G, 状态,"已逾期") = 220000+46000 | F18: 模板口径，AR与AP合并统计
A19: 【预算执行 — 月度口径】
A20: 本月支出预算(年度/12) | B20: 340000 | C20: 月度汇总!F11←预算执行!C13/12 | D20: 年度预算合计4080000 ÷ 12 | E20: =预算执行!C13/12 = 4080000/12 | F20: 待财务复核：均摊口径，未考虑季节性
A21: 本月预算差异(预算-实际) | B21: 172000 | C21: 月度汇总!G11 | D21: 月度预算-月度实际支出 | E21: =F11-C11 = 340000-168000 | F21: 有利差异(节约)
A22: 本月预算执行率 | B22: 0.4941 | C22: 月度汇总!H11 | D22: 月度实际支出/月度预算 | E22: =IFERROR(C11/F11,0) = 168000/340000 | F22: 百分比
A23: 【预算执行 — 年度累计口径(1-7月)】
A24: 累计实际支出合计 | B24: 608400 | C24: 预算执行!P13 | D24: 列D:O各月实际之和 | E24: =SUM(预算执行!J5:J12 各月累计) = 1-7月支出合计 | F24: —
A25: 年度预算合计 | B25: 4080000 | C25: 预算执行!C13 | D25: 列C年度预算之和 | E25: =SUM(预算执行!C5:C12) | F25: —
A26: 累计预算执行率 | B26: 0.1491 | C26: 预算执行!R13 | D26: 累计实际/年度预算 | E26: =IFERROR(P13/C13,0) = 608400/4080000 | F26: 远低于58.33%时间进度
A27: 年度时间进度 | B27: 0.5833 | C27: 预算执行!S5:S12 | D27: 7/12 | E27: =7/12 | F27: —

Sheet 数据检查清单
A1: 2026年7月报表 — 数据检查清单
A2: 检查范围：财务流水(r5-r22) / 预算执行(r5-r13) / 应收应付(r4-r9) / 月度汇总 / 管理看板。检查人：财务报表专员(AI辅助)。检查日期：2026-07-19。
A3: 检查项 | B3: 检查方法 | C3: 检查结果 | D3: 涉及行/单号 | E3: 处理建议
A4: 流水行数与月份 | B4: 扫描财务流水A列非空行 | C4: 18条流水，月份覆盖2026-01~2026-07，本月(07)5条 | D4: r5-r22 | E4: 正常
A5: 重复数据 | B5: 按(摘要+金额+部门+费用类别)查重 | C5: 无完全重复行 | D5: — | E5: 正常
A6: 必填字段空值 | B6: 检查日期/业务类型/部门/费用类别/金额 | C6: 无空值 | D6: r5-r22 | E6: 正常
A7: 金额合法性 | B7: 金额(含税)>0 | C7: 全部为正数 | D7: r5-r22 | E7: 正常
A8: 税额公式 | B8: 复核 税额=含税×税率/(1+税率) | C8: 18行全部吻合(误差<0.01) | D8: r5-r22 | E8: 正常
A9: 未税金额公式 | B9: 复核 未税=含税-税额 | C9: 18行全部吻合 | D9: r5-r22 | E9: 正常
A10: 异常检查列(Q列) | B10: 扫描非"正常"项 | C10: 2条"缺发票" | D10: r15(运维费46000), r21(市场推广费18000) | E10: 待财务复核：补齐发票
A11: 缺发票(支出未收票) | B11: 支出且发票状态=未收票 | C11: 2条 | D11: r15, r21 | E11: 待财务复核：催收发票
A12: 未付款支出 | B12: 支付状态=未付款 | C12: 3条 | D12: r15(46000), r20(42000), r21(18000) | E12: r20已收票可排款；r15/r21待补发票
A13: 未开票收入 | B13: 收入且发票状态=未开票 | C13: 1条 | D13: r22(项目服务收入220000) | E13: 待财务复核：尽快开票确认收入
A14: 未收款收入 | B14: 支付状态=未收款 | C14: 1条 | D14: r22(220000) | E14: 待财务复核：开票后催收
... A22: 金额单位与小数位 | B22: 全部金额保留两位小数 | C22: 已统一 | D22: 全表 | E22: 正常

Sheet 图表分析
A1: 2026年7月 费用结构与经营情况图表分析
A2: 说明：图片由 Python(matplotlib) 按财务流水原始数据生成，数据口径与"公式溯源"表一致；金额单位元，保留两位小数。
A3: 图1 7月支出费用结构(饼图) | E3: 图2 7月收支与净现金流
A27: 图3 7月收入结构 | E27: 图4 7月预算 vs 实际
A51: 图5 1-7月各费用类别累计预算执行率 vs 时间进度
