Workbook

Sheet 财务流水
A1: 财务流水明细台账 | B1: 财务流水明细台账 | C1: 财务流水明细台账 | D1: 财务流水明细台账 | E1: 财务流水明细台账 | F1: 财务流水明细台账 | G1: 财务流水明细台账 | H1: 财务流水明细台账 | I1: 财务流水明细台账 | J1: 财务流水明细台账 | K1: 财务流水明细台账 | L1: 财务流水明细台账 | M1: 财务流水明细台账 | N1: 财务流水明细台账 | O1: 财务流水明细台账 | P1: 财务流水明细台账 | Q1: 财务流水明细台账
A2: 财务流水明细台账 | B2: 财务流水明细台账 | C2: 财务流水明细台账 | D2: 财务流水明细台账 | E2: 财务流水明细台账 | F2: 财务流水明细台账 | G2: 财务流水明细台账 | H2: 财务流水明细台账 | I2: 财务流水明细台账 | J2: 财务流水明细台账 | K2: 财务流水明细台账 | L2: 财务流水明细台账 | M2: 财务流水明细台账 | N2: 财务流水明细台账 | O2: 财务流水明细台账 | P2: 财务流水明细台账 | Q2: 财务流水明细台账
A3: 填写提示：金额统一录入正数，业务类型决定收入或支出；黄色列为人工录入，绿色列为自动计算。
A4: 日期 | B4: 月份 | C4: 业务类型 | D4: 部门 | E4: 项目/站点 | F4: 费用类别 | G4: 摘要 | H4: 对方单位 | I4: 发票状态 | J4: 支付状态 | K4: 付款方式 | L4: 金额(含税) | M4: 税率 | N4: 税额 | O4: 未税金额 | P4: 经办人 | Q4: 异常检查
A5: 46028 | B5: =TEXT(A5,"yyyy-mm") -> 2026-01 | C5: 收入 | D5: 运营部 | E5: 金坛体育馆站 | F5: 充电服务收入 | G5: 1月充电服务收入 | H5: 常州某运营公司 | I5: 已开票 | J5: 已收款 | K5: 银行转账 | L5: 286000 | M5: 0.06 | N5: =IFERROR(L5*M5/(1+M5),0) -> 16188.679 | O5: =L5-N5 -> 269811.32 | P5: 张敏 | Q5: =IF(A5="","",IF(OR(L5<=0,C5="",D5="",F5=""),"需检查",IF(AND(C5="支出",I5="未收票"),"缺发票","正常"))) -> 正常
A6: 46032 | B6: =TEXT(A6,"yyyy-mm") -> 2026-01 | C6: 支出 | D6: 研发部 | E6: AI平台一期 | F6: 软件服务费 | G6: 模型API及云资源 | H6: 某科技公司 | I6: 已收票 | J6: 已付款 | K6: 银行转账 | L6: 38000 | M6: 0.06 | N6: =IFERROR(L6*M6/(1+M6),0) -> 2150.9434 | O6: =L6-N6 -> 35849.057 | P6: 李强 | Q6: =IF(A6="","",IF(OR(L6<=0,C6="",D6="",F6=""),"需检查",IF(AND(C6="支出",I6="未收票"),"缺发票","正常"))) -> 正常
A7: 46040 | B7: =TEXT(A7,"yyyy-mm") -> 2026-01 | C7: 支出 | D7: 运营部 | E7: 金坛体育馆站 | F7: 电费 | G7: 1月场站购电费 | H7: 国网常州供电公司 | I7: 已收票 | J7: 已付款 | K7: 银行转账 | L7: 92000 | M7: 0.13 | N7: =IFERROR(L7*M7/(1+M7),0) -> 10584.071 | O7: =L7-N7 -> 81415.929 | P7: 王芳 | Q7: =IF(A7="","",IF(OR(L7<=0,C7="",D7="",F7=""),"需检查",IF(AND(C7="支出",I7="未收票"),"缺发票","正常"))) -> 正常
A8: 46061 | B8: =TEXT(A8,"yyyy-mm") -> 2026-02 | C8: 收入 | D8: 运营部 | E8: 弘阳广场站 | F8: 充电服务收入 | G8: 2月充电服务收入 | H8: 常州某运营公司 | I8: 已开票 | J8: 已收款 | K8: 银行转账 | L8: 301000 | M8: 0.06 | N8: =IFERROR(L8*M8/(1+M8),0) -> 17037.736 | O8: =L8-N8 -> 283962.26 | P8: 张敏 | Q8: =IF(A8="","",IF(OR(L8<=0,C8="",D8="",F8=""),"需检查",IF(AND(C8="支出",I8="未收票"),"缺发票","正常"))) -> 正常
A9: 46068 | B9: =TEXT(A9,"yyyy-mm") -> 2026-02 | C9: 支出 | D9: 市场部 | E9: 品牌推广 | F9: 市场推广费 | G9: 行业会议展位费 | H9: 某会展公司 | I9: 已收票 | J9: 已付款 | K9: 公司卡 | L9: 26000 | M9: 0.06 | N9: =IFERROR(L9*M9/(1+M9),0) -> 1471.6981 | O9: =L9-N9 -> 24528.302 | P9: 赵晨 | Q9: =IF(A9="","",IF(OR(L9<=0,C9="",D9="",F9=""),"需检查",IF(AND(C9="支出",I9="未收票"),"缺发票","正常"))) -> 正常
A10: 46086 | B10: =TEXT(A10,"yyyy-mm") -> 2026-03 | C10: 收入 | D10: 项目部 | E10: 储能改造项目 | F10: 项目服务收入 | G10: 储能EMS实施款 | H10: 某能源公司 | I10: 已开票 | J10: 部分收款 | K10: 银行转账 | L10: 420000 | M10: 0.06 | N10: =IFERROR(L10*M10/(1+M10),0) -> 23773.585 | O10: =L10-N10 -> 396226.42 | P10: 陈杰 | Q10: =IF(A10="","",IF(OR(L10<=0,C10="",D10="",F10=""),"需检查",IF(AND(C10="支出",I10="未收票"),"缺发票","正常"))) -> 正常
A11: 46092 | B11: =TEXT(A11,"yyyy-mm") -> 2026-03 | C11: 支出 | D11: 项目部 | E11: 储能改造项目 | F11: 设备采购 | G11: 储能计量设备采购 | H11: 某设备公司 | I11: 已收票 | J11: 已付款 | K11: 银行转账 | L11: 185000 | M11: 0.13 | N11: =IFERROR(L11*M11/(1+M11),0) -> 21283.186 | O11: =L11-N11 -> 163716.81 | P11: 陈杰 | Q11: =IF(A11="","",IF(OR(L11<=0,C11="",D11="",F11=""),"需检查",IF(AND(C11="支出",I11="未收票"),"缺发票","正常"))) -> 正常
A12: 46121 | B12: =TEXT(A12,"yyyy-mm") -> 2026-04 | C12: 支出 | D12: 行政部 | E12: 总部 | F12: 办公费 | G12: 办公耗材采购 | H12: 某商贸公司 | I12: 已收票 | J12: 已付款 | K12: 公司卡 | L12: 12800 | M12: 0.13 | N12: =IFERROR(L12*M12/(1+M12),0) -> 1472.5664 | O12: =L12-N12 -> 11327.434 | P12: 刘悦 | Q12: =IF(A12="","",IF(OR(L12<=0,C12="",D12="",F12=""),"需检查",IF(AND(C12="支出",I12="未收票"),"缺发票","正常"))) -> 正常
A13: 46137 | B13: =TEXT(A13,"yyyy-mm") -> 2026-04 | C13: 收入 | D13: 运营部 | E13: 凤凰谷站 | F13: 充电服务收入 | G13: 4月充电服务收入 | H13: 常州某运营公司 | I13: 已开票 | J13: 已收款 | K13: 银行转账 | L13: 318000 | M13: 0.06 | N13: =IFERROR(L13*M13/(1+M13),0) -> 18000 | O13: =L13-N13 -> 300000 | P13: 张敏 | Q13: =IF(A13="","",IF(OR(L13<=0,C13="",D13="",F13=""),"需检查",IF(AND(C13="支出",I13="未收票"),"缺发票","正常"))) -> 正常
A14: 46148 | B14: =TEXT(A14,"yyyy-mm") -> 2026-05 | C14: 支出 | D14: 研发部 | E14: AI平台一期 | F14: 差旅费 | G14: 项目调研差旅 | H14: 个人报销 | I14: 无需发票 | J14: 已付款 | K14: 个人垫付 | L14: 8600 | M14: 0 | N14: =IFERROR(L14*M14/(1+M14),0) -> 0 | O14: =L14-N14 -> 8600 | P14: 李强 | Q14: =IF(A14="","",IF(OR(L14<=0,C14="",D14="",F14=""),"需检查",IF(AND(C14="支出",I14="未收票"),"缺发票","正常"))) -> 正常
A15: 46162 | B15: =TEXT(A15,"yyyy-mm") -> 2026-05 | C15: 支出 | D15: 运营部 | E15: 凤凰谷站 | F15: 运维费 | G15: 充电桩年度巡检 | H15: 某运维公司 | I15: 未收票 | J15: 未付款 | K15: 银行转账 | L15: 46000 | M15: 0.06 | N15: =IFERROR(L15*M15/(1+M15),0) -> 2603.7736 | O15: =L15-N15 -> 43396.226 | P15: 王芳 | Q15: =IF(A15="","",IF(OR(L15<=0,C15="",D15="",F15=""),"需检查",IF(AND(C15="支出",I15="未收票"),"缺发票","正常"))) -> 缺发票
A16: 46176 | B16: =TEXT(A16,"yyyy-mm") -> 2026-06 | C16: 收入 | D16: 项目部 | E16: 数据平台项目 | F16: 项目服务收入 | G16: 数据平台二期里程碑款 | H16: 某电力公司 | I16: 已开票 | J16: 已收款 | K16: 银行转账 | L16: 560000 | M16: 0.06 | N16: =IFERROR(L16*M16/(1+M16),0) -> 31698.113 | O16: =L16-N16 -> 528301.89 | P16: 陈杰 | Q16: =IF(A16="","",IF(OR(L16<=0,C16="",D16="",F16=""),"需检查",IF(AND(C16="支出",I16="未收票"),"缺发票","正常"))) -> 正常
... A22: 46218 | B22: =TEXT(A22,"yyyy-mm") -> 2026-07 | C22: 收入 | D22: 项目部 | E22: 数据平台项目 | F22: 项目服务收入 | G22: 验收尾款 | H22: 某电力公司 | I22: 未开票 | J22: 未收款 | K22: 银行转账 | L22: 220000 | M22: 0.06 | N22: =IFERROR(L22*M22/(1+M22),0) -> 12452.83 | O22: =L22-N22 -> 207547.17 | P22: 陈杰 | Q22: =IF(A22="","",IF(OR(L22<=0,C22="",D22="",F22=""),"需检查",IF(AND(C22="支出",I22="未收票"),"缺发票","正常"))) -> 正常
B23: =TEXT(A23,"yyyy-mm") -> 1900-01 | N23: =IFERROR(L23*M23/(1+M23),0) -> 0 | O23: =L23-N23 -> 0 | Q23: =IF(A23="","",IF(OR(L23<=0,C23="",D23="",F23=""),"需检查",IF(AND(C23="支出",I23="未收票"),"缺发票","正常")))
B24: =TEXT(A24,"yyyy-mm") -> 1900-01 | N24: =IFERROR(L24*M24/(1+M24),0) -> 0 | O24: =L24-N24 -> 0 | Q24: =IF(A24="","",IF(OR(L24<=0,C24="",D24="",F24=""),"需检查",IF(AND(C24="支出",I24="未收票"),"缺发票","正常")))
B25: =TEXT(A25,"yyyy-mm") -> 1900-01 | N25: =IFERROR(L25*M25/(1+M25),0) -> 0 | O25: =L25-N25 -> 0 | Q25: =IF(A25="","",IF(OR(L25<=0,C25="",D25="",F25=""),"需检查",IF(AND(C25="支出",I25="未收票"),"缺发票","正常")))
B26: =TEXT(A26,"yyyy-mm") -> 1900-01 | N26: =IFERROR(L26*M26/(1+M26),0) -> 0 | O26: =L26-N26 -> 0 | Q26: =IF(A26="","",IF(OR(L26<=0,C26="",D26="",F26=""),"需检查",IF(AND(C26="支出",I26="未收票"),"缺发票","正常")))
B27: =TEXT(A27,"yyyy-mm") -> 1900-01 | N27: =IFERROR(L27*M27/(1+M27),0) -> 0 | O27: =L27-N27 -> 0 | Q27: =IF(A27="","",IF(OR(L27<=0,C27="",D27="",F27=""),"需检查",IF(AND(C27="支出",I27="未收票"),"缺发票","正常")))
B28: =TEXT(A28,"yyyy-mm") -> 1900-01 | N28: =IFERROR(L28*M28/(1+M28),0) -> 0 | O28: =L28-N28 -> 0 | Q28: =IF(A28="","",IF(OR(L28<=0,C28="",D28="",F28=""),"需检查",IF(AND(C28="支出",I28="未收票"),"缺发票","正常")))
B29: =TEXT(A29,"yyyy-mm") -> 1900-01 | N29: =IFERROR(L29*M29/(1+M29),0) -> 0 | O29: =L29-N29 -> 0 | Q29: =IF(A29="","",IF(OR(L29<=0,C29="",D29="",F29=""),"需检查",IF(AND(C29="支出",I29="未收票"),"缺发票","正常")))
B30: =TEXT(A30,"yyyy-mm") -> 1900-01 | N30: =IFERROR(L30*M30/(1+M30),0) -> 0 | O30: =L30-N30 -> 0 | Q30: =IF(A30="","",IF(OR(L30<=0,C30="",D30="",F30=""),"需检查",IF(AND(C30="支出",I30="未收票"),"缺发票","正常")))
B31: =TEXT(A31,"yyyy-mm") -> 1900-01 | N31: =IFERROR(L31*M31/(1+M31),0) -> 0 | O31: =L31-N31 -> 0 | Q31: =IF(A31="","",IF(OR(L31<=0,C31="",D31="",F31=""),"需检查",IF(AND(C31="支出",I31="未收票"),"缺发票","正常")))
B32: =TEXT(A32,"yyyy-mm") -> 1900-01 | N32: =IFERROR(L32*M32/(1+M32),0) -> 0 | O32: =L32-N32 -> 0 | Q32: =IF(A32="","",IF(OR(L32<=0,C32="",D32="",F32=""),"需检查",IF(AND(C32="支出",I32="未收票"),"缺发票","正常")))
B33: =TEXT(A33,"yyyy-mm") -> 1900-01 | N33: =IFERROR(L33*M33/(1+M33),0) -> 0 | O33: =L33-N33 -> 0 | Q33: =IF(A33="","",IF(OR(L33<=0,C33="",D33="",F33=""),"需检查",IF(AND(C33="支出",I33="未收票"),"缺发票","正常")))
B34: =TEXT(A34,"yyyy-mm") -> 1900-01 | N34: =IFERROR(L34*M34/(1+M34),0) -> 0 | O34: =L34-N34 -> 0 | Q34: =IF(A34="","",IF(OR(L34<=0,C34="",D34="",F34=""),"需检查",IF(AND(C34="支出",I34="未收票"),"缺发票","正常")))
... B204: =TEXT(A204,"yyyy-mm") -> 1900-01 | N204: =IFERROR(L204*M204/(1+M204),0) -> 0 | O204: =L204-N204 -> 0 | Q204: =IF(A204="","",IF(OR(L204<=0,C204="",D204="",F204=""),"需检查",IF(AND(C204="支出",I204="未收票"),"缺发票","正常")))

Sheet 预算执行
A1: 年度预算执行表 | B1: 年度预算执行表 | C1: 年度预算执行表 | D1: 年度预算执行表 | E1: 年度预算执行表 | F1: 年度预算执行表 | G1: 年度预算执行表 | H1: 年度预算执行表 | I1: 年度预算执行表 | J1: 年度预算执行表 | K1: 年度预算执行表 | L1: 年度预算执行表 | M1: 年度预算执行表 | N1: 年度预算执行表 | O1: 年度预算执行表 | P1: 年度预算执行表 | Q1: 年度预算执行表 | R1: 年度预算执行表 | S1: 年度预算执行表 | T1: 年度预算执行表 | U1: 年度预算执行表
A2: 年度预算执行表 | B2: 年度预算执行表 | C2: 年度预算执行表 | D2: 年度预算执行表 | E2: 年度预算执行表 | F2: 年度预算执行表 | G2: 年度预算执行表 | H2: 年度预算执行表 | I2: 年度预算执行表 | J2: 年度预算执行表 | K2: 年度预算执行表 | L2: 年度预算执行表 | M2: 年度预算执行表 | N2: 年度预算执行表 | O2: 年度预算执行表 | P2: 年度预算执行表 | Q2: 年度预算执行表 | R2: 年度预算执行表 | S2: 年度预算执行表 | T2: 年度预算执行表 | U2: 年度预算执行表
A3: 黄色列为年度预算输入；各月实际取自“财务流水”中的支出数据。
A4: 部门 | B4: 费用类别 | C4: 年度预算 | D4: 1月实际 | E4: 2月实际 | F4: 3月实际 | G4: 4月实际 | H4: 5月实际 | I4: 6月实际 | J4: 7月实际 | K4: 8月实际 | L4: 9月实际 | M4: 10月实际 | N4: 11月实际 | O4: 12月实际 | P4: 累计实际 | Q4: 剩余预算 | R4: 执行率 | S4: 年度进度 | T4: 偏差状态 | U4: 责任人
A5: 运营部 | B5: 电费 | C5: 1200000 | D5: =SUMIFS(财务流水!$L$5:$L$204,财务流水!$B$5:$B$204,"2026-01",财务流水!$C$5:$C$204,"支出",财务流水!$D$5:$D$204,$A5,财务流水!$F$5:$F$204,$B5) -> 92000 | E5: =SUMIFS(财务流水!$L$5:$L$204,财务流水!$B$5:$B$204,"2026-02",财务流水!$C$5:$C$204,"支出",财务流水!$D$5:$D$204,$A5,财务流水!$F$5:$F$204,$B5) -> 0 | F5: =SUMIFS(财务流水!$L$5:$L$204,财务流水!$B$5:$B$204,"2026-03",财务流水!$C$5:$C$204,"支出",财务流水!$D$5:$D$204,$A5,财务流水!$F$5:$F$204,$B5) -> 0 | G5: =SUMIFS(财务流水!$L$5:$L$204,财务流水!$B$5:$B$204,"2026-04",财务流水!$C$5:$C$204,"支出",财务流水!$D$5:$D$204,$A5,财务流水!$F$5:$F$204,$B5) -> 0 | H5: =SUMIFS(财务流水!$L$5:$L$204,财务流水!$B$5:$B$204,"2026-05",财务流水!$C$5:$C$204,"支出",财务流水!$D$5:$D$204,$A5,财务流水!$F$5:$F$204,$B5) -> 0 | I5: =SUMIFS(财务流水!$L$5:$L$204,财务流水!$B$5:$B$204,"2026-06",财务流水!$C$5:$C$204,"支出",财务流水!$D$5:$D$204,$A5,财务流水!$F$5:$F$204,$B5) -> 0 | J5: =SUMIFS(财务流水!$L$5:$L$204,财务流水!$B$5:$B$204,"2026-07",财务流水!$C$5:$C$204,"支出",财务流水!$D$5:$D$204,$A5,财务流水!$F$5:$F$204,$B5) -> 108000 | K5: =SUMIFS(财务流水!$L$5:$L$204,财务流水!$B$5:$B$204,"2026-08",财务流水!$C$5:$C$204,"支出",财务流水!$D$5:$D$204,$A5,财务流水!$F$5:$F$204,$B5) -> 0 | L5: =SUMIFS(财务流水!$L$5:$L$204,财务流水!$B$5:$B$204,"2026-09",财务流水!$C$5:$C$204,"支出",财务流水!$D$5:$D$204,$A5,财务流水!$F$5:$F$204,$B5) -> 0 | M5: =SUMIFS(财务流水!$L$5:$L$204,财务流水!$B$5:$B$204,"2026-10",财务流水!$C$5:$C$204,"支出",财务流水!$D$5:$D$204,$A5,财务流水!$F$5:$F$204,$B5) -> 0 | N5: =SUMIFS(财务流水!$L$5:$L$204,财务流水!$B$5:$B$204,"2026-11",财务流水!$C$5:$C$204,"支出",财务流水!$D$5:$D$204,$A5,财务流水!$F$5:$F$204,$B5) -> 0 | O5: =SUMIFS(财务流水!$L$5:$L$204,财务流水!$B$5:$B$204,"2026-12",财务流水!$C$5:$C$204,"支出",财务流水!$D$5:$D$204,$A5,财务流水!$F$5:$F$204,$B5) -> 0 | P5: =SUM(D5:O5) -> 200000 | Q5: =C5-P5 -> 1000000 | R5: =IFERROR(P5/C5,0) -> 0.16666667 | S5: =7/12 -> 0.58333333 | T5: =IF(R5>S5+10%,"超进度",IF(R5<S5-10%,"低于进度","正常")) -> 低于进度 | U5: 王芳
A6: 运营部 | B6: 运维费 | C6: 480000 | D6: =SUMIFS(财务流水!$L$5:$L$204,财务流水!$B$5:$B$204,"2026-01",财务流水!$C$5:$C$204,"支出",财务流水!$D$5:$D$204,$A6,财务流水!$F$5:$F$204,$B6) -> 0 | E6: =SUMIFS(财务流水!$L$5:$L$204,财务流水!$B$5:$B$204,"2026-02",财务流水!$C$5:$C$204,"支出",财务流水!$D$5:$D$204,$A6,财务流水!$F$5:$F$204,$B6) -> 0 | F6: =SUMIFS(财务流水!$L$5:$L$204,财务流水!$B$5:$B$204,"2026-03",财务流水!$C$5:$C$204,"支出",财务流水!$D$5:$D$204,$A6,财务流水!$F$5:$F$204,$B6) -> 0 | G6: =SUMIFS(财务流水!$L$5:$L$204,财务流水!$B$5:$B$204,"2026-04",财务流水!$C$5:$C$204,"支出",财务流水!$D$5:$D$204,$A6,财务流水!$F$5:$F$204,$B6) -> 0 | H6: =SUMIFS(财务流水!$L$5:$L$204,财务流水!$B$5:$B$204,"2026-05",财务流水!$C$5:$C$204,"支出",财务流水!$D$5:$D$204,$A6,财务流水!$F$5:$F$204,$B6) -> 46000 | I6: =SUMIFS(财务流水!$L$5:$L$204,财务流水!$B$5:$B$204,"2026-06",财务流水!$C$5:$C$204,"支出",财务流水!$D$5:$D$204,$A6,财务流水!$F$5:$F$204,$B6) -> 0 | J6: =SUMIFS(财务流水!$L$5:$L$204,财务流水!$B$5:$B$204,"2026-07",财务流水!$C$5:$C$204,"支出",财务流水!$D$5:$D$204,$A6,财务流水!$F$5:$F$204,$B6) -> 0 | K6: =SUMIFS(财务流水!$L$5:$L$204,财务流水!$B$5:$B$204,"2026-08",财务流水!$C$5:$C$204,"支出",财务流水!$D$5:$D$204,$A6,财务流水!$F$5:$F$204,$B6) -> 0 | L6: =SUMIFS(财务流水!$L$5:$L$204,财务流水!$B$5:$B$204,"2026-09",财务流水!$C$5:$C$204,"支出",财务流水!$D$5:$D$204,$A6,财务流水!$F$5:$F$204,$B6) -> 0 | M6: =SUMIFS(财务流水!$L$5:$L$204,财务流水!$B$5:$B$204,"2026-10",财务流水!$C$5:$C$204,"支出",财务流水!$D$5:$D$204,$A6,财务流水!$F$5:$F$204,$B6) -> 0 | N6: =SUMIFS(财务流水!$L$5:$L$204,财务流水!$B$5:$B$204,"2026-11",财务流水!$C$5:$C$204,"支出",财务流水!$D$5:$D$204,$A6,财务流水!$F$5:$F$204,$B6) -> 0 | O6: =SUMIFS(财务流水!$L$5:$L$204,财务流水!$B$5:$B$204,"2026-12",财务流水!$C$5:$C$204,"支出",财务流水!$D$5:$D$204,$A6,财务流水!$F$5:$F$204,$B6) -> 0 | P6: =SUM(D6:O6) -> 46000 | Q6: =C6-P6 -> 434000 | R6: =IFERROR(P6/C6,0) -> 0.095833333 | S6: =7/12 -> 0.58333333 | T6: =IF(R6>S6+10%,"超进度",IF(R6<S6-10%,"低于进度","正常")) -> 低于进度 | U6: 王芳
A7: 研发部 | B7: 软件服务费 | C7: 600000 | D7: =SUMIFS(财务流水!$L$5:$L$204,财务流水!$B$5:$B$204,"2026-01",财务流水!$C$5:$C$204,"支出",财务流水!$D$5:$D$204,$A7,财务流水!$F$5:$F$204,$B7) -> 38000 | E7: =SUMIFS(财务流水!$L$5:$L$204,财务流水!$B$5:$B$204,"2026-02",财务流水!$C$5:$C$204,"支出",财务流水!$D$5:$D$204,$A7,财务流水!$F$5:$F$204,$B7) -> 0 | F7: =SUMIFS(财务流水!$L$5:$L$204,财务流水!$B$5:$B$204,"2026-03",财务流水!$C$5:$C$204,"支出",财务流水!$D$5:$D$204,$A7,财务流水!$F$5:$F$204,$B7) -> 0 | G7: =SUMIFS(财务流水!$L$5:$L$204,财务流水!$B$5:$B$204,"2026-04",财务流水!$C$5:$C$204,"支出",财务流水!$D$5:$D$204,$A7,财务流水!$F$5:$F$204,$B7) -> 0 | H7: =SUMIFS(财务流水!$L$5:$L$204,财务流水!$B$5:$B$204,"2026-05",财务流水!$C$5:$C$204,"支出",财务流水!$D$5:$D$204,$A7,财务流水!$F$5:$F$204,$B7) -> 0 | I7: =SUMIFS(财务流水!$L$5:$L$204,财务流水!$B$5:$B$204,"2026-06",财务流水!$C$5:$C$204,"支出",财务流水!$D$5:$D$204,$A7,财务流水!$F$5:$F$204,$B7) -> 0 | J7: =SUMIFS(财务流水!$L$5:$L$204,财务流水!$B$5:$B$204,"2026-07",财务流水!$C$5:$C$204,"支出",财务流水!$D$5:$D$204,$A7,财务流水!$F$5:$F$204,$B7) -> 42000 | K7: =SUMIFS(财务流水!$L$5:$L$204,财务流水!$B$5:$B$204,"2026-08",财务流水!$C$5:$C$204,"支出",财务流水!$D$5:$D$204,$A7,财务流水!$F$5:$F$204,$B7) -> 0 | L7: =SUMIFS(财务流水!$L$5:$L$204,财务流水!$B$5:$B$204,"2026-09",财务流水!$C$5:$C$204,"支出",财务流水!$D$5:$D$204,$A7,财务流水!$F$5:$F$204,$B7) -> 0 | M7: =SUMIFS(财务流水!$L$5:$L$204,财务流水!$B$5:$B$204,"2026-10",财务流水!$C$5:$C$204,"支出",财务流水!$D$5:$D$204,$A7,财务流水!$F$5:$F$204,$B7) -> 0 | N7: =SUMIFS(财务流水!$L$5:$L$204,财务流水!$B$5:$B$204,"2026-11",财务流水!$C$5:$C$204,"支出",财务流水!$D$5:$D$204,$A7,财务流水!$F$5:$F$204,$B7) -> 0 | O7: =SUMIFS(财务流水!$L$5:$L$204,财务流水!$B$5:$B$204,"2026-12",财务流水!$C$5:$C$204,"支出",财务流水!$D$5:$D$204,$A7,财务流水!$F$5:$F$204,$B7) -> 0 | P7: =SUM(D7:O7) -> 80000 | Q7: =C7-P7 -> 520000 | R7: =IFERROR(P7/C7,0) -> 0.13333333 | S7: =7/12 -> 0.58333333 | T7: =IF(R7>S7+10%,"超进度",IF(R7<S7-10%,"低于进度","正常")) -> 低于进度 | U7: 李强
A8: 研发部 | B8: 差旅费 | C8: 120000 | D8: =SUMIFS(财务流水!$L$5:$L$204,财务流水!$B$5:$B$204,"2026-01",财务流水!$C$5:$C$204,"支出",财务流水!$D$5:$D$204,$A8,财务流水!$F$5:$F$204,$B8) -> 0 | E8: =SUMIFS(财务流水!$L$5:$L$204,财务流水!$B$5:$B$204,"2026-02",财务流水!$C$5:$C$204,"支出",财务流水!$D$5:$D$204,$A8,财务流水!$F$5:$F$204,$B8) -> 0 | F8: =SUMIFS(财务流水!$L$5:$L$204,财务流水!$B$5:$B$204,"2026-03",财务流水!$C$5:$C$204,"支出",财务流水!$D$5:$D$204,$A8,财务流水!$F$5:$F$204,$B8) -> 0 | G8: =SUMIFS(财务流水!$L$5:$L$204,财务流水!$B$5:$B$204,"2026-04",财务流水!$C$5:$C$204,"支出",财务流水!$D$5:$D$204,$A8,财务流水!$F$5:$F$204,$B8) -> 0 | H8: =SUMIFS(财务流水!$L$5:$L$204,财务流水!$B$5:$B$204,"2026-05",财务流水!$C$5:$C$204,"支出",财务流水!$D$5:$D$204,$A8,财务流水!$F$5:$F$204,$B8) -> 8600 | I8: =SUMIFS(财务流水!$L$5:$L$204,财务流水!$B$5:$B$204,"2026-06",财务流水!$C$5:$C$204,"支出",财务流水!$D$5:$D$204,$A8,财务流水!$F$5:$F$204,$B8) -> 0 | J8: =SUMIFS(财务流水!$L$5:$L$204,财务流水!$B$5:$B$204,"2026-07",财务流水!$C$5:$C$204,"支出",财务流水!$D$5:$D$204,$A8,财务流水!$F$5:$F$204,$B8) -> 0 | K8: =SUMIFS(财务流水!$L$5:$L$204,财务流水!$B$5:$B$204,"2026-08",财务流水!$C$5:$C$204,"支出",财务流水!$D$5:$D$204,$A8,财务流水!$F$5:$F$204,$B8) -> 0 | L8: =SUMIFS(财务流水!$L$5:$L$204,财务流水!$B$5:$B$204,"2026-09",财务流水!$C$5:$C$204,"支出",财务流水!$D$5:$D$204,$A8,财务流水!$F$5:$F$204,$B8) -> 0 | M8: =SUMIFS(财务流水!$L$5:$L$204,财务流水!$B$5:$B$204,"2026-10",财务流水!$C$5:$C$204,"支出",财务流水!$D$5:$D$204,$A8,财务流水!$F$5:$F$204,$B8) -> 0 | N8: =SUMIFS(财务流水!$L$5:$L$204,财务流水!$B$5:$B$204,"2026-11",财务流水!$C$5:$C$204,"支出",财务流水!$D$5:$D$204,$A8,财务流水!$F$5:$F$204,$B8) -> 0 | O8: =SUMIFS(财务流水!$L$5:$L$204,财务流水!$B$5:$B$204,"2026-12",财务流水!$C$5:$C$204,"支出",财务流水!$D$5:$D$204,$A8,财务流水!$F$5:$F$204,$B8) -> 0 | P8: =SUM(D8:O8) -> 8600 | Q8: =C8-P8 -> 111400 | R8: =IFERROR(P8/C8,0) -> 0.071666667 | S8: =7/12 -> 0.58333333 | T8: =IF(R8>S8+10%,"超进度",IF(R8<S8-10%,"低于进度","正常")) -> 低于进度 | U8: 李强
A9: 项目部 | B9: 设备采购 | C9: 900000 | D9: =SUMIFS(财务流水!$L$5:$L$204,财务流水!$B$5:$B$204,"2026-01",财务流水!$C$5:$C$204,"支出",财务流水!$D$5:$D$204,$A9,财务流水!$F$5:$F$204,$B9) -> 0 | E9: =SUMIFS(财务流水!$L$5:$L$204,财务流水!$B$5:$B$204,"2026-02",财务流水!$C$5:$C$204,"支出",财务流水!$D$5:$D$204,$A9,财务流水!$F$5:$F$204,$B9) -> 0 | F9: =SUMIFS(财务流水!$L$5:$L$204,财务流水!$B$5:$B$204,"2026-03",财务流水!$C$5:$C$204,"支出",财务流水!$D$5:$D$204,$A9,财务流水!$F$5:$F$204,$B9) -> 185000 | G9: =SUMIFS(财务流水!$L$5:$L$204,财务流水!$B$5:$B$204,"2026-04",财务流水!$C$5:$C$204,"支出",财务流水!$D$5:$D$204,$A9,财务流水!$F$5:$F$204,$B9) -> 0 | H9: =SUMIFS(财务流水!$L$5:$L$204,财务流水!$B$5:$B$204,"2026-05",财务流水!$C$5:$C$204,"支出",财务流水!$D$5:$D$204,$A9,财务流水!$F$5:$F$204,$B9) -> 0 | I9: =SUMIFS(财务流水!$L$5:$L$204,财务流水!$B$5:$B$204,"2026-06",财务流水!$C$5:$C$204,"支出",财务流水!$D$5:$D$204,$A9,财务流水!$F$5:$F$204,$B9) -> 0 | J9: =SUMIFS(财务流水!$L$5:$L$204,财务流水!$B$5:$B$204,"2026-07",财务流水!$C$5:$C$204,"支出",财务流水!$D$5:$D$204,$A9,财务流水!$F$5:$F$204,$B9) -> 0 | K9: =SUMIFS(财务流水!$L$5:$L$204,财务流水!$B$5:$B$204,"2026-08",财务流水!$C$5:$C$204,"支出",财务流水!$D$5:$D$204,$A9,财务流水!$F$5:$F$204,$B9) -> 0 | L9: =SUMIFS(财务流水!$L$5:$L$204,财务流水!$B$5:$B$204,"2026-09",财务流水!$C$5:$C$204,"支出",财务流水!$D$5:$D$204,$A9,财务流水!$F$5:$F$204,$B9) -> 0 | M9: =SUMIFS(财务流水!$L$5:$L$204,财务流水!$B$5:$B$204,"2026-10",财务流水!$C$5:$C$204,"支出",财务流水!$D$5:$D$204,$A9,财务流水!$F$5:$F$204,$B9) -> 0 | N9: =SUMIFS(财务流水!$L$5:$L$204,财务流水!$B$5:$B$204,"2026-11",财务流水!$C$5:$C$204,"支出",财务流水!$D$5:$D$204,$A9,财务流水!$F$5:$F$204,$B9) -> 0 | O9: =SUMIFS(财务流水!$L$5:$L$204,财务流水!$B$5:$B$204,"2026-12",财务流水!$C$5:$C$204,"支出",财务流水!$D$5:$D$204,$A9,财务流水!$F$5:$F$204,$B9) -> 0 | P9: =SUM(D9:O9) -> 185000 | Q9: =C9-P9 -> 715000 | R9: =IFERROR(P9/C9,0) -> 0.20555556 | S9: =7/12 -> 0.58333333 | T9: =IF(R9>S9+10%,"超进度",IF(R9<S9-10%,"低于进度","正常")) -> 低于进度 | U9: 陈杰
A10: 市场部 | B10: 市场推广费 | C10: 360000 | D10: =SUMIFS(财务流水!$L$5:$L$204,财务流水!$B$5:$B$204,"2026-01",财务流水!$C$5:$C$204,"支出",财务流水!$D$5:$D$204,$A10,财务流水!$F$5:$F$204,$B10) -> 0 | E10: =SUMIFS(财务流水!$L$5:$L$204,财务流水!$B$5:$B$204,"2026-02",财务流水!$C$5:$C$204,"支出",财务流水!$D$5:$D$204,$A10,财务流水!$F$5:$F$204,$B10) -> 26000 | F10: =SUMIFS(财务流水!$L$5:$L$204,财务流水!$B$5:$B$204,"2026-03",财务流水!$C$5:$C$204,"支出",财务流水!$D$5:$D$204,$A10,财务流水!$F$5:$F$204,$B10) -> 0 | G10: =SUMIFS(财务流水!$L$5:$L$204,财务流水!$B$5:$B$204,"2026-04",财务流水!$C$5:$C$204,"支出",财务流水!$D$5:$D$204,$A10,财务流水!$F$5:$F$204,$B10) -> 0 | H10: =SUMIFS(财务流水!$L$5:$L$204,财务流水!$B$5:$B$204,"2026-05",财务流水!$C$5:$C$204,"支出",财务流水!$D$5:$D$204,$A10,财务流水!$F$5:$F$204,$B10) -> 0 | I10: =SUMIFS(财务流水!$L$5:$L$204,财务流水!$B$5:$B$204,"2026-06",财务流水!$C$5:$C$204,"支出",财务流水!$D$5:$D$204,$A10,财务流水!$F$5:$F$204,$B10) -> 0 | J10: =SUMIFS(财务流水!$L$5:$L$204,财务流水!$B$5:$B$204,"2026-07",财务流水!$C$5:$C$204,"支出",财务流水!$D$5:$D$204,$A10,财务流水!$F$5:$F$204,$B10) -> 18000 | K10: =SUMIFS(财务流水!$L$5:$L$204,财务流水!$B$5:$B$204,"2026-08",财务流水!$C$5:$C$204,"支出",财务流水!$D$5:$D$204,$A10,财务流水!$F$5:$F$204,$B10) -> 0 | L10: =SUMIFS(财务流水!$L$5:$L$204,财务流水!$B$5:$B$204,"2026-09",财务流水!$C$5:$C$204,"支出",财务流水!$D$5:$D$204,$A10,财务流水!$F$5:$F$204,$B10) -> 0 | M10: =SUMIFS(财务流水!$L$5:$L$204,财务流水!$B$5:$B$204,"2026-10",财务流水!$C$5:$C$204,"支出",财务流水!$D$5:$D$204,$A10,财务流水!$F$5:$F$204,$B10) -> 0 | N10: =SUMIFS(财务流水!$L$5:$L$204,财务流水!$B$5:$B$204,"2026-11",财务流水!$C$5:$C$204,"支出",财务流水!$D$5:$D$204,$A10,财务流水!$F$5:$F$204,$B10) -> 0 | O10: =SUMIFS(财务流水!$L$5:$L$204,财务流水!$B$5:$B$204,"2026-12",财务流水!$C$5:$C$204,"支出",财务流水!$D$5:$D$204,$A10,财务流水!$F$5:$F$204,$B10) -> 0 | P10: =SUM(D10:O10) -> 44000 | Q10: =C10-P10 -> 316000 | R10: =IFERROR(P10/C10,0) -> 0.12222222 | S10: =7/12 -> 0.58333333 | T10: =IF(R10>S10+10%,"超进度",IF(R10<S10-10%,"低于进度","正常")) -> 低于进度 | U10: 赵晨
A11: 行政部 | B11: 办公费 | C11: 180000 | D11: =SUMIFS(财务流水!$L$5:$L$204,财务流水!$B$5:$B$204,"2026-01",财务流水!$C$5:$C$204,"支出",财务流水!$D$5:$D$204,$A11,财务流水!$F$5:$F$204,$B11) -> 0 | E11: =SUMIFS(财务流水!$L$5:$L$204,财务流水!$B$5:$B$204,"2026-02",财务流水!$C$5:$C$204,"支出",财务流水!$D$5:$D$204,$A11,财务流水!$F$5:$F$204,$B11) -> 0 | F11: =SUMIFS(财务流水!$L$5:$L$204,财务流水!$B$5:$B$204,"2026-03",财务流水!$C$5:$C$204,"支出",财务流水!$D$5:$D$204,$A11,财务流水!$F$5:$F$204,$B11) -> 0 | G11: =SUMIFS(财务流水!$L$5:$L$204,财务流水!$B$5:$B$204,"2026-04",财务流水!$C$5:$C$204,"支出",财务流水!$D$5:$D$204,$A11,财务流水!$F$5:$F$204,$B11) -> 12800 | H11: =SUMIFS(财务流水!$L$5:$L$204,财务流水!$B$5:$B$204,"2026-05",财务流水!$C$5:$C$204,"支出",财务流水!$D$5:$D$204,$A11,财务流水!$F$5:$F$204,$B11) -> 0 | I11: =SUMIFS(财务流水!$L$5:$L$204,财务流水!$B$5:$B$204,"2026-06",财务流水!$C$5:$C$204,"支出",财务流水!$D$5:$D$204,$A11,财务流水!$F$5:$F$204,$B11) -> 0 | J11: =SUMIFS(财务流水!$L$5:$L$204,财务流水!$B$5:$B$204,"2026-07",财务流水!$C$5:$C$204,"支出",财务流水!$D$5:$D$204,$A11,财务流水!$F$5:$F$204,$B11) -> 0 | K11: =SUMIFS(财务流水!$L$5:$L$204,财务流水!$B$5:$B$204,"2026-08",财务流水!$C$5:$C$204,"支出",财务流水!$D$5:$D$204,$A11,财务流水!$F$5:$F$204,$B11) -> 0 | L11: =SUMIFS(财务流水!$L$5:$L$204,财务流水!$B$5:$B$204,"2026-09",财务流水!$C$5:$C$204,"支出",财务流水!$D$5:$D$204,$A11,财务流水!$F$5:$F$204,$B11) -> 0 | M11: =SUMIFS(财务流水!$L$5:$L$204,财务流水!$B$5:$B$204,"2026-10",财务流水!$C$5:$C$204,"支出",财务流水!$D$5:$D$204,$A11,财务流水!$F$5:$F$204,$B11) -> 0 | N11: =SUMIFS(财务流水!$L$5:$L$204,财务流水!$B$5:$B$204,"2026-11",财务流水!$C$5:$C$204,"支出",财务流水!$D$5:$D$204,$A11,财务流水!$F$5:$F$204,$B11) -> 0 | O11: =SUMIFS(财务流水!$L$5:$L$204,财务流水!$B$5:$B$204,"2026-12",财务流水!$C$5:$C$204,"支出",财务流水!$D$5:$D$204,$A11,财务流水!$F$5:$F$204,$B11) -> 0 | P11: =SUM(D11:O11) -> 12800 | Q11: =C11-P11 -> 167200 | R11: =IFERROR(P11/C11,0) -> 0.071111111 | S11: =7/12 -> 0.58333333 | T11: =IF(R11>S11+10%,"超进度",IF(R11<S11-10%,"低于进度","正常")) -> 低于进度 | U11: 刘悦
A12: 人力资源部 | B12: 培训费 | C12: 240000 | D12: =SUMIFS(财务流水!$L$5:$L$204,财务流水!$B$5:$B$204,"2026-01",财务流水!$C$5:$C$204,"支出",财务流水!$D$5:$D$204,$A12,财务流水!$F$5:$F$204,$B12) -> 0 | E12: =SUMIFS(财务流水!$L$5:$L$204,财务流水!$B$5:$B$204,"2026-02",财务流水!$C$5:$C$204,"支出",财务流水!$D$5:$D$204,$A12,财务流水!$F$5:$F$204,$B12) -> 0 | F12: =SUMIFS(财务流水!$L$5:$L$204,财务流水!$B$5:$B$204,"2026-03",财务流水!$C$5:$C$204,"支出",财务流水!$D$5:$D$204,$A12,财务流水!$F$5:$F$204,$B12) -> 0 | G12: =SUMIFS(财务流水!$L$5:$L$204,财务流水!$B$5:$B$204,"2026-04",财务流水!$C$5:$C$204,"支出",财务流水!$D$5:$D$204,$A12,财务流水!$F$5:$F$204,$B12) -> 0 | H12: =SUMIFS(财务流水!$L$5:$L$204,财务流水!$B$5:$B$204,"2026-05",财务流水!$C$5:$C$204,"支出",财务流水!$D$5:$D$204,$A12,财务流水!$F$5:$F$204,$B12) -> 0 | I12: =SUMIFS(财务流水!$L$5:$L$204,财务流水!$B$5:$B$204,"2026-06",财务流水!$C$5:$C$204,"支出",财务流水!$D$5:$D$204,$A12,财务流水!$F$5:$F$204,$B12) -> 32000 | J12: =SUMIFS(财务流水!$L$5:$L$204,财务流水!$B$5:$B$204,"2026-07",财务流水!$C$5:$C$204,"支出",财务流水!$D$5:$D$204,$A12,财务流水!$F$5:$F$204,$B12) -> 0 | K12: =SUMIFS(财务流水!$L$5:$L$204,财务流水!$B$5:$B$204,"2026-08",财务流水!$C$5:$C$204,"支出",财务流水!$D$5:$D$204,$A12,财务流水!$F$5:$F$204,$B12) -> 0 | L12: =SUMIFS(财务流水!$L$5:$L$204,财务流水!$B$5:$B$204,"2026-09",财务流水!$C$5:$C$204,"支出",财务流水!$D$5:$D$204,$A12,财务流水!$F$5:$F$204,$B12) -> 0 | M12: =SUMIFS(财务流水!$L$5:$L$204,财务流水!$B$5:$B$204,"2026-10",财务流水!$C$5:$C$204,"支出",财务流水!$D$5:$D$204,$A12,财务流水!$F$5:$F$204,$B12) -> 0 | N12: =SUMIFS(财务流水!$L$5:$L$204,财务流水!$B$5:$B$204,"2026-11",财务流水!$C$5:$C$204,"支出",财务流水!$D$5:$D$204,$A12,财务流水!$F$5:$F$204,$B12) -> 0 | O12: =SUMIFS(财务流水!$L$5:$L$204,财务流水!$B$5:$B$204,"2026-12",财务流水!$C$5:$C$204,"支出",财务流水!$D$5:$D$204,$A12,财务流水!$F$5:$F$204,$B12) -> 0 | P12: =SUM(D12:O12) -> 32000 | Q12: =C12-P12 -> 208000 | R12: =IFERROR(P12/C12,0) -> 0.13333333 | S12: =7/12 -> 0.58333333 | T12: =IF(R12>S12+10%,"超进度",IF(R12<S12-10%,"低于进度","正常")) -> 低于进度 | U12: 孙静
A13: 合计 | C13: =SUM(C5:C12) -> 4080000 | D13: =SUM(D5:D12) -> 130000 | E13: =SUM(E5:E12) -> 26000 | F13: =SUM(F5:F12) -> 185000 | G13: =SUM(G5:G12) -> 12800 | H13: =SUM(H5:H12) -> 54600 | I13: =SUM(I5:I12) -> 32000 | J13: =SUM(J5:J12) -> 168000 | ... Q13: =SUM(Q5:Q12) -> 3471600 | R13: =IFERROR(P13/C13,0) -> 0.14911765 | S13: =7/12 -> 0.58333333 | T13: =IF(R13>S13+10%,"超进度",IF(R13<S13-10%,"低于进度","正常")) -> 低于进度

Sheet 应收应付
A1: 应收应付与账期跟踪 | B1: 应收应付与账期跟踪 | C1: 应收应付与账期跟踪 | D1: 应收应付与账期跟踪 | E1: 应收应付与账期跟踪 | F1: 应收应付与账期跟踪 | G1: 应收应付与账期跟踪 | H1: 应收应付与账期跟踪 | I1: 应收应付与账期跟踪 | J1: 应收应付与账期跟踪 | K1: 应收应付与账期跟踪 | L1: 应收应付与账期跟踪
A2: 应收应付与账期跟踪 | B2: 应收应付与账期跟踪 | C2: 应收应付与账期跟踪 | D2: 应收应付与账期跟踪 | E2: 应收应付与账期跟踪 | F2: 应收应付与账期跟踪 | G2: 应收应付与账期跟踪 | H2: 应收应付与账期跟踪 | I2: 应收应付与账期跟踪 | J2: 应收应付与账期跟踪 | K2: 应收应付与账期跟踪 | L2: 应收应付与账期跟踪
A3: 单号 | B3: 类型 | C3: 对方单位 | D3: 项目 | E3: 合同金额 | F3: 已收/已付 | G3: 未结金额 | H3: 到期日 | I3: 状态 | J3: 逾期天数 | K3: 负责人 | L3: 下一步动作
A4: AR-26001 | B4: 应收 | C4: 某能源公司 | D4: 储能改造项目 | E4: 420000 | F4: 200000 | G4: =E4-F4 -> 220000 | H4: 46203 | I4: =IF(A4="","",IF(G4<=0,"已结清",IF(H4<TODAY(),"已逾期","未到期"))) -> 已逾期 | J4: =IF(OR(A4="",G4<=0),0,MAX(0,TODAY()-H4)) -> 19 | K4: 陈杰 | L4: 催收剩余里程碑款
A5: AR-26002 | B5: 应收 | C5: 某电力公司 | D5: 数据平台项目 | E5: 780000 | F5: 560000 | G5: =E5-F5 -> 220000 | H5: 46223 | I5: =IF(A5="","",IF(G5<=0,"已结清",IF(H5<TODAY(),"已逾期","未到期"))) -> 未到期 | J5: =IF(OR(A5="",G5<=0),0,MAX(0,TODAY()-H5)) -> 0 | K5: 陈杰 | L5: 验收后开票催收
A6: AR-26003 | B6: 应收 | C6: 常州某运营公司 | D6: 7月充电服务 | E6: 335000 | F6: 335000 | G6: =E6-F6 -> 0 | H6: 46213 | I6: =IF(A6="","",IF(G6<=0,"已结清",IF(H6<TODAY(),"已逾期","未到期"))) -> 已结清 | J6: =IF(OR(A6="",G6<=0),0,MAX(0,TODAY()-H6)) -> 0 | K6: 张敏 | L6: 已结清归档
A7: AP-26001 | B7: 应付 | C7: 某科技公司 | D7: AI平台API费用 | E7: 42000 | F7: 0 | G7: =E7-F7 -> 42000 | H7: 46234 | I7: =IF(A7="","",IF(G7<=0,"已结清",IF(H7<TODAY(),"已逾期","未到期"))) -> 未到期 | J7: =IF(OR(A7="",G7<=0),0,MAX(0,TODAY()-H7)) -> 0 | K7: 李强 | L7: 核对发票后付款
A8: AP-26002 | B8: 应付 | C8: 某传媒公司 | D8: 品牌内容制作 | E8: 18000 | F8: 0 | G8: =E8-F8 -> 18000 | H8: 46228 | I8: =IF(A8="","",IF(G8<=0,"已结清",IF(H8<TODAY(),"已逾期","未到期"))) -> 未到期 | J8: =IF(OR(A8="",G8<=0),0,MAX(0,TODAY()-H8)) -> 0 | K8: 赵晨 | L8: 补齐发票与验收材料
A9: AP-26003 | B9: 应付 | C9: 某运维公司 | D9: 凤凰谷年度巡检 | E9: 46000 | F9: 0 | G9: =E9-F9 -> 46000 | H9: 46188 | I9: =IF(A9="","",IF(G9<=0,"已结清",IF(H9<TODAY(),"已逾期","未到期"))) -> 已逾期 | J9: =IF(OR(A9="",G9<=0),0,MAX(0,TODAY()-H9)) -> 34 | K9: 王芳 | L9: 确认巡检报告并排款
G10: =E10-F10 -> 0 | I10: =IF(A10="","",IF(G10<=0,"已结清",IF(H10<TODAY(),"已逾期","未到期"))) | J10: =IF(OR(A10="",G10<=0),0,MAX(0,TODAY()-H10)) -> 0
G11: =E11-F11 -> 0 | I11: =IF(A11="","",IF(G11<=0,"已结清",IF(H11<TODAY(),"已逾期","未到期"))) | J11: =IF(OR(A11="",G11<=0),0,MAX(0,TODAY()-H11)) -> 0
G12: =E12-F12 -> 0 | I12: =IF(A12="","",IF(G12<=0,"已结清",IF(H12<TODAY(),"已逾期","未到期"))) | J12: =IF(OR(A12="",G12<=0),0,MAX(0,TODAY()-H12)) -> 0
G13: =E13-F13 -> 0 | I13: =IF(A13="","",IF(G13<=0,"已结清",IF(H13<TODAY(),"已逾期","未到期"))) | J13: =IF(OR(A13="",G13<=0),0,MAX(0,TODAY()-H13)) -> 0
G14: =E14-F14 -> 0 | I14: =IF(A14="","",IF(G14<=0,"已结清",IF(H14<TODAY(),"已逾期","未到期"))) | J14: =IF(OR(A14="",G14<=0),0,MAX(0,TODAY()-H14)) -> 0
G15: =E15-F15 -> 0 | I15: =IF(A15="","",IF(G15<=0,"已结清",IF(H15<TODAY(),"已逾期","未到期"))) | J15: =IF(OR(A15="",G15<=0),0,MAX(0,TODAY()-H15)) -> 0
G16: =E16-F16 -> 0 | I16: =IF(A16="","",IF(G16<=0,"已结清",IF(H16<TODAY(),"已逾期","未到期"))) | J16: =IF(OR(A16="",G16<=0),0,MAX(0,TODAY()-H16)) -> 0
G17: =E17-F17 -> 0 | I17: =IF(A17="","",IF(G17<=0,"已结清",IF(H17<TODAY(),"已逾期","未到期"))) | J17: =IF(OR(A17="",G17<=0),0,MAX(0,TODAY()-H17)) -> 0
G18: =E18-F18 -> 0 | I18: =IF(A18="","",IF(G18<=0,"已结清",IF(H18<TODAY(),"已逾期","未到期"))) | J18: =IF(OR(A18="",G18<=0),0,MAX(0,TODAY()-H18)) -> 0
G19: =E19-F19 -> 0 | I19: =IF(A19="","",IF(G19<=0,"已结清",IF(H19<TODAY(),"已逾期","未到期"))) | J19: =IF(OR(A19="",G19<=0),0,MAX(0,TODAY()-H19)) -> 0
G20: =E20-F20 -> 0 | I20: =IF(A20="","",IF(G20<=0,"已结清",IF(H20<TODAY(),"已逾期","未到期"))) | J20: =IF(OR(A20="",G20<=0),0,MAX(0,TODAY()-H20)) -> 0
G21: =E21-F21 -> 0 | I21: =IF(A21="","",IF(G21<=0,"已结清",IF(H21<TODAY(),"已逾期","未到期"))) | J21: =IF(OR(A21="",G21<=0),0,MAX(0,TODAY()-H21)) -> 0
... G103: =E103-F103 -> 0 | I103: =IF(A103="","",IF(G103<=0,"已结清",IF(H103<TODAY(),"已逾期","未到期"))) | J103: =IF(OR(A103="",G103<=0),0,MAX(0,TODAY()-H103)) -> 0

Sheet 月度汇总
A1: 2026年月度经营财务汇总 | B1: 2026年月度经营财务汇总 | C1: 2026年月度经营财务汇总 | D1: 2026年月度经营财务汇总 | E1: 2026年月度经营财务汇总 | F1: 2026年月度经营财务汇总 | G1: 2026年月度经营财务汇总 | H1: 2026年月度经营财务汇总
A2: 2026年月度经营财务汇总 | B2: 2026年月度经营财务汇总 | C2: 2026年月度经营财务汇总 | D2: 2026年月度经营财务汇总 | E2: 2026年月度经营财务汇总 | F2: 2026年月度经营财务汇总 | G2: 2026年月度经营财务汇总 | H2: 2026年月度经营财务汇总
A4: 月份 | B4: 收入 | C4: 支出 | D4: 净现金流 | E4: 累计净现金流 | F4: 支出预算 | G4: 预算差异 | H4: 预算执行率
A5: 2026-01 | B5: =SUMIFS(财务流水!$L$5:$L$204,财务流水!$B$5:$B$204,A5,财务流水!$C$5:$C$204,"收入") -> 286000 | C5: =SUMIFS(财务流水!$L$5:$L$204,财务流水!$B$5:$B$204,A5,财务流水!$C$5:$C$204,"支出") -> 130000 | D5: =B5-C5 -> 156000 | E5: =D5 -> 156000 | F5: =预算执行!$C$13/12 -> 340000 | G5: =F5-C5 -> 210000 | H5: =IFERROR(C5/F5,0) -> 0.38235294
A6: 2026-02 | B6: =SUMIFS(财务流水!$L$5:$L$204,财务流水!$B$5:$B$204,A6,财务流水!$C$5:$C$204,"收入") -> 301000 | C6: =SUMIFS(财务流水!$L$5:$L$204,财务流水!$B$5:$B$204,A6,财务流水!$C$5:$C$204,"支出") -> 26000 | D6: =B6-C6 -> 275000 | E6: =E5+D6 -> 431000 | F6: =预算执行!$C$13/12 -> 340000 | G6: =F6-C6 -> 314000 | H6: =IFERROR(C6/F6,0) -> 0.076470588
A7: 2026-03 | B7: =SUMIFS(财务流水!$L$5:$L$204,财务流水!$B$5:$B$204,A7,财务流水!$C$5:$C$204,"收入") -> 420000 | C7: =SUMIFS(财务流水!$L$5:$L$204,财务流水!$B$5:$B$204,A7,财务流水!$C$5:$C$204,"支出") -> 185000 | D7: =B7-C7 -> 235000 | E7: =E6+D7 -> 666000 | F7: =预算执行!$C$13/12 -> 340000 | G7: =F7-C7 -> 155000 | H7: =IFERROR(C7/F7,0) -> 0.54411765
A8: 2026-04 | B8: =SUMIFS(财务流水!$L$5:$L$204,财务流水!$B$5:$B$204,A8,财务流水!$C$5:$C$204,"收入") -> 318000 | C8: =SUMIFS(财务流水!$L$5:$L$204,财务流水!$B$5:$B$204,A8,财务流水!$C$5:$C$204,"支出") -> 12800 | D8: =B8-C8 -> 305200 | E8: =E7+D8 -> 971200 | F8: =预算执行!$C$13/12 -> 340000 | G8: =F8-C8 -> 327200 | H8: =IFERROR(C8/F8,0) -> 0.037647059
A9: 2026-05 | B9: =SUMIFS(财务流水!$L$5:$L$204,财务流水!$B$5:$B$204,A9,财务流水!$C$5:$C$204,"收入") -> 0 | C9: =SUMIFS(财务流水!$L$5:$L$204,财务流水!$B$5:$B$204,A9,财务流水!$C$5:$C$204,"支出") -> 54600 | D9: =B9-C9 -> -54600 | E9: =E8+D9 -> 916600 | F9: =预算执行!$C$13/12 -> 340000 | G9: =F9-C9 -> 285400 | H9: =IFERROR(C9/F9,0) -> 0.16058824
A10: 2026-06 | B10: =SUMIFS(财务流水!$L$5:$L$204,财务流水!$B$5:$B$204,A10,财务流水!$C$5:$C$204,"收入") -> 560000 | C10: =SUMIFS(财务流水!$L$5:$L$204,财务流水!$B$5:$B$204,A10,财务流水!$C$5:$C$204,"支出") -> 32000 | D10: =B10-C10 -> 528000 | E10: =E9+D10 -> 1444600 | F10: =预算执行!$C$13/12 -> 340000 | G10: =F10-C10 -> 308000 | H10: =IFERROR(C10/F10,0) -> 0.094117647
A11: 2026-07 | B11: =SUMIFS(财务流水!$L$5:$L$204,财务流水!$B$5:$B$204,A11,财务流水!$C$5:$C$204,"收入") -> 555000 | C11: =SUMIFS(财务流水!$L$5:$L$204,财务流水!$B$5:$B$204,A11,财务流水!$C$5:$C$204,"支出") -> 168000 | D11: =B11-C11 -> 387000 | E11: =E10+D11 -> 1831600 | F11: =预算执行!$C$13/12 -> 340000 | G11: =F11-C11 -> 172000 | H11: =IFERROR(C11/F11,0) -> 0.49411765
A12: 2026-08 | B12: =SUMIFS(财务流水!$L$5:$L$204,财务流水!$B$5:$B$204,A12,财务流水!$C$5:$C$204,"收入") -> 0 | C12: =SUMIFS(财务流水!$L$5:$L$204,财务流水!$B$5:$B$204,A12,财务流水!$C$5:$C$204,"支出") -> 0 | D12: =B12-C12 -> 0 | E12: =E11+D12 -> 1831600 | F12: =预算执行!$C$13/12 -> 340000 | G12: =F12-C12 -> 340000 | H12: =IFERROR(C12/F12,0) -> 0
A13: 2026-09 | B13: =SUMIFS(财务流水!$L$5:$L$204,财务流水!$B$5:$B$204,A13,财务流水!$C$5:$C$204,"收入") -> 0 | C13: =SUMIFS(财务流水!$L$5:$L$204,财务流水!$B$5:$B$204,A13,财务流水!$C$5:$C$204,"支出") -> 0 | D13: =B13-C13 -> 0 | E13: =E12+D13 -> 1831600 | F13: =预算执行!$C$13/12 -> 340000 | G13: =F13-C13 -> 340000 | H13: =IFERROR(C13/F13,0) -> 0
A14: 2026-10 | B14: =SUMIFS(财务流水!$L$5:$L$204,财务流水!$B$5:$B$204,A14,财务流水!$C$5:$C$204,"收入") -> 0 | C14: =SUMIFS(财务流水!$L$5:$L$204,财务流水!$B$5:$B$204,A14,财务流水!$C$5:$C$204,"支出") -> 0 | D14: =B14-C14 -> 0 | E14: =E13+D14 -> 1831600 | F14: =预算执行!$C$13/12 -> 340000 | G14: =F14-C14 -> 340000 | H14: =IFERROR(C14/F14,0) -> 0
A15: 2026-11 | B15: =SUMIFS(财务流水!$L$5:$L$204,财务流水!$B$5:$B$204,A15,财务流水!$C$5:$C$204,"收入") -> 0 | C15: =SUMIFS(财务流水!$L$5:$L$204,财务流水!$B$5:$B$204,A15,财务流水!$C$5:$C$204,"支出") -> 0 | D15: =B15-C15 -> 0 | E15: =E14+D15 -> 1831600 | F15: =预算执行!$C$13/12 -> 340000 | G15: =F15-C15 -> 340000 | H15: =IFERROR(C15/F15,0) -> 0
A16: 2026-12 | B16: =SUMIFS(财务流水!$L$5:$L$204,财务流水!$B$5:$B$204,A16,财务流水!$C$5:$C$204,"收入") -> 0 | C16: =SUMIFS(财务流水!$L$5:$L$204,财务流水!$B$5:$B$204,A16,财务流水!$C$5:$C$204,"支出") -> 0 | D16: =B16-C16 -> 0 | E16: =E15+D16 -> 1831600 | F16: =预算执行!$C$13/12 -> 340000 | G16: =F16-C16 -> 340000 | H16: =IFERROR(C16/F16,0) -> 0
A17: 全年合计 | B17: =SUM(B5:B16) -> 2440000 | C17: =SUM(C5:C16) -> 608400 | D17: =SUM(D5:D16) -> 1831600 | E17: =E16 -> 1831600 | F17: =SUM(F5:F16) -> 4080000 | G17: =SUM(G5:G16) -> 3471600 | H17: =IFERROR(C17/F17,0) -> 0.14911765

Sheet 管理看板
A1: 财务管理看板 | B1: 财务管理看板 | C1: 财务管理看板 | D1: 财务管理看板 | E1: 财务管理看板 | F1: 财务管理看板 | G1: 财务管理看板 | H1: 财务管理看板 | I1: 财务管理看板 | J1: 财务管理看板 | K1: 财务管理看板 | L1: 财务管理看板
A2: 财务管理看板 | B2: 财务管理看板 | C2: 财务管理看板 | D2: 财务管理看板 | E2: 财务管理看板 | F2: 财务管理看板 | G2: 财务管理看板 | H2: 财务管理看板 | I2: 财务管理看板 | J2: 财务管理看板 | K2: 财务管理看板 | L2: 财务管理看板
A3: 查看月份 | B3: 2026-07
A5: 本月收入 | D5: 本月支出 | G5: 净现金流 | J5: 逾期未结
A6: =SUMIFS(财务流水!$L$5:$L$204,财务流水!$B$5:$B$204,$B$3,财务流水!$C$5:$C$204,"收入") -> 555000 | D6: =SUMIFS(财务流水!$L$5:$L$204,财务流水!$B$5:$B$204,$B$3,财务流水!$C$5:$C$204,"支出") -> 168000 | G6: =A6-D6 -> 387000 | J6: =SUMIFS(应收应付!$G$4:$G$103,应收应付!$I$4:$I$103,"已逾期") -> 266000
A8: 本月费用结构 | B8: 本月费用结构 | C8: 本月费用结构 | D8: 本月费用结构 | E8: 本月费用结构 | F8: 本月费用结构
A9: 费用类别 | B9: 金额
A10: 电费 | B10: =SUMIFS(财务流水!$L$5:$L$204,财务流水!$B$5:$B$204,$B$3,财务流水!$C$5:$C$204,"支出",财务流水!$F$5:$F$204,A10) -> 108000
A11: 运维费 | B11: =SUMIFS(财务流水!$L$5:$L$204,财务流水!$B$5:$B$204,$B$3,财务流水!$C$5:$C$204,"支出",财务流水!$F$5:$F$204,A11) -> 0
A12: 软件服务费 | B12: =SUMIFS(财务流水!$L$5:$L$204,财务流水!$B$5:$B$204,$B$3,财务流水!$C$5:$C$204,"支出",财务流水!$F$5:$F$204,A12) -> 42000
A13: 差旅费 | B13: =SUMIFS(财务流水!$L$5:$L$204,财务流水!$B$5:$B$204,$B$3,财务流水!$C$5:$C$204,"支出",财务流水!$F$5:$F$204,A13) -> 0
A14: 设备采购 | B14: =SUMIFS(财务流水!$L$5:$L$204,财务流水!$B$5:$B$204,$B$3,财务流水!$C$5:$C$204,"支出",财务流水!$F$5:$F$204,A14) -> 0
A15: 市场推广费 | B15: =SUMIFS(财务流水!$L$5:$L$204,财务流水!$B$5:$B$204,$B$3,财务流水!$C$5:$C$204,"支出",财务流水!$F$5:$F$204,A15) -> 18000
A16: 办公费 | B16: =SUMIFS(财务流水!$L$5:$L$204,财务流水!$B$5:$B$204,$B$3,财务流水!$C$5:$C$204,"支出",财务流水!$F$5:$F$204,A16) -> 0
A17: 培训费 | B17: =SUMIFS(财务流水!$L$5:$L$204,财务流水!$B$5:$B$204,$B$3,财务流水!$C$5:$C$204,"支出",财务流水!$F$5:$F$204,A17) -> 0
A20: 管理提示 | B20: 管理提示 | C20: 管理提示 | D20: 管理提示 | E20: 管理提示 | F20: 管理提示
A21: =IF(J6>0,"存在逾期未结款项，请优先核对“应收应付”工作表。",IF(D6>A6,"本月支出高于收入，请关注现金流与预算执行。","本月现金流为正，继续跟踪未开票和未付款事项。")) -> 存在逾期未结款项，请优先核对“应收应付”工作表。
G22: 月份 | H22: 净现金流
G23: =月度汇总!A5 -> 2026-01 | H23: =月度汇总!D5 -> 156000
G24: =月度汇总!A6 -> 2026-02 | H24: =月度汇总!D6 -> 275000
G25: =月度汇总!A7 -> 2026-03 | H25: =月度汇总!D7 -> 235000
G26: =月度汇总!A8 -> 2026-04 | H26: =月度汇总!D8 -> 305200
G27: =月度汇总!A9 -> 2026-05 | H27: =月度汇总!D9 -> -54600
G28: =月度汇总!A10 -> 2026-06 | H28: =月度汇总!D10 -> 528000
G29: =月度汇总!A11 -> 2026-07 | H29: =月度汇总!D11 -> 387000
G30: =月度汇总!A12 -> 2026-08 | H30: =月度汇总!D12 -> 0
G31: =月度汇总!A13 -> 2026-09 | H31: =月度汇总!D13 -> 0
G32: =月度汇总!A14 -> 2026-10 | H32: =月度汇总!D14 -> 0
G33: =月度汇总!A15 -> 2026-11 | H33: =月度汇总!D15 -> 0
G34: =月度汇总!A16 -> 2026-12 | H34: =月度汇总!D16 -> 0
